[
  {
    "scrip": "ALUMINIUM",
    "lot": "5 MT",
    "price": 136.15,
    "nrml": 62969,
    "mis": 31484,
    "co_lower": 1,
    "co_upper": 1.9
  },
  {
    "scrip": "COPPER",
    "lot": "2.5 MT",
    "price": 439.7,
    "nrml": 101680,
    "mis": 50840,
    "co_lower": 1,
    "co_upper": 1.9
  },
  {
    "scrip": "COTTON",
    "lot": "25 BALES",
    "price": 16740,
    "nrml": 38711,
    "mis": 0,
    "co_lower": 1,
    "co_upper": 1.9
  },
  {
    "scrip": "CPO",
    "lot": "10 MT",
    "price": 667,
    "nrml": 78639,
    "mis": 0,
    "co_lower": 1,
    "co_upper": 1.9
  },
  {
    "scrip": "CRUDEOIL",
    "lot": "100 BBL",
    "price": 2888,
    "nrml": 292410,
    "mis": 146205,
    "co_lower": 1,
    "co_upper": 1.9
  },
  {
    "scrip": "GOLD",
    "lot": "1 KGS",
    "price": 46594,
    "nrml": 443108,
    "mis": 221554,
    "co_lower": 1,
    "co_upper": 1.9
  },
  {
    "scrip": "GOLDGUINEA",
    "lot": "8 GRMS",
    "price": 37582,
    "nrml": 3476,
    "mis": 1738,
    "co_lower": 1,
    "co_upper": 1.9
  },
  {
    "scrip": "GOLDM",
    "lot": "100 GRMS",
    "price": 46584,
    "nrml": 43090,
    "mis": 21545,
    "co_lower": 1,
    "co_upper": 1.9
  },
  {
    "scrip": "GOLDPETAL",
    "lot": "1 GRMS",
    "price": 4690,
    "nrml": 433,
    "mis": 216,
    "co_lower": 1,
    "co_upper": 1.9
  },
  {
    "scrip": "KAPAS",
    "lot": "4 MT",
    "price": 1050,
    "nrml": 23310,
    "mis": 11655,
    "co_lower": 1,
    "co_upper": 1.9
  },
  {
    "scrip": "LEAD",
    "lot": "5 MT",
    "price": 140.6,
    "nrml": 79087,
    "mis": 39543,
    "co_lower": 1,
    "co_upper": 1.9
  },
  {
    "scrip": "MENTHAOIL",
    "lot": "1080 KGS",
    "price": 1055,
    "nrml": 150970,
    "mis": 0,
    "co_lower": 1,
    "co_upper": 1.9
  },
  {
    "scrip": "NATURALGAS",
    "lot": "1250 MMBTU",
    "price": 133.8,
    "nrml": 33700,
    "mis": 16850,
    "co_lower": 1,
    "co_upper": 1.9
  },
  {
    "scrip": "NICKEL",
    "lot": "1500 KGS",
    "price": 974.1,
    "nrml": 164379,
    "mis": 82189,
    "co_lower": 1,
    "co_upper": 1.9
  },
  {
    "scrip": "SILVER",
    "lot": "30 KGS",
    "price": 48099,
    "nrml": 174455,
    "mis": 87227,
    "co_lower": 1,
    "co_upper": 1.9
  },
  {
    "scrip": "SILVERM",
    "lot": "5 KGS",
    "price": 49109,
    "nrml": 29268,
    "mis": 14634,
    "co_lower": 1,
    "co_upper": 1.9
  },
  {
    "scrip": "SILVERMIC",
    "lot": "1 KGS",
    "price": 49110,
    "nrml": 5623,
    "mis": 2811,
    "co_lower": 1,
    "co_upper": 1.9
  },
  {
    "scrip": "ZINC",
    "lot": "5 MT",
    "price": 163.35,
    "nrml": 91884,
    "mis": 45942,
    "co_lower": 1,
    "co_upper": 1.9
  }
]