[{"tradingsymbol":"3M INDIA LIMITED","mis_multiplier":"6.00","nrml_multiplier":"1"},{"tradingsymbol":"5paisa Capital Ltd","mis_multiplier":"2.50","nrml_multiplier":"1"},{"tradingsymbol":"AARTI DRUGS LTD.","mis_multiplier":"2.00","nrml_multiplier":"1"},{"tradingsymbol":"AARTI INDUSTRIES LTD","mis_multiplier":"3.00","nrml_multiplier":"1"},{"tradingsymbol":"AAVAS Financiers Limited","mis_multiplier":"2.50","nrml_multiplier":"1"},{"tradingsymbol":"ABAN OFFSHORE LTD.","mis_multiplier":"4.00","nrml_multiplier":"1"},{"tradingsymbol":"ABB INDIA LIMITED","mis_multiplier":"8.00","nrml_multiplier":"1"},{"tradingsymbol":"ABBOTT INDIA LIMITED","mis_multiplier":"5.00","nrml_multiplier":"1"},{"tradingsymbol":"ACC LIMITED","mis_multiplier":"10.00","nrml_multiplier":"1"},{"tradingsymbol":"ACCELYA KALE SOLUTION LTD","mis_multiplier":"4.00","nrml_multiplier":"1"},{"tradingsymbol":"ADANI ENTERPRISES LIMITED","mis_multiplier":"5.00","nrml_multiplier":"1"},{"tradingsymbol":"Adani Gas Ltd","mis_multiplier":"4.00","nrml_multiplier":"1"},{"tradingsymbol":"ADANI PORT & SEZ LTD","mis_multiplier":"5.00","nrml_multiplier":"1"},{"tradingsymbol":"ADANI POWER LTD","mis_multiplier":"5.00","nrml_multiplier":"1"},{"tradingsymbol":"Adani Transmission Limited","mis_multiplier":"4.00","nrml_multiplier":"1"},{"tradingsymbol":"Aditya Birla Capital Ltd","mis_multiplier":"5.00","nrml_multiplier":"1"},{"tradingsymbol":"Aditya Birla Fashion and Retai","mis_multiplier":"2.00","nrml_multiplier":"1"},{"tradingsymbol":"Advanced Enzyme Technologies L","mis_multiplier":"2.00","nrml_multiplier":"1"},{"tradingsymbol":"AEGIS LOGISTICS LTD","mis_multiplier":"1.00","nrml_multiplier":"1"},{"tradingsymbol":"AIA ENGINEERING LIMITED","mis_multiplier":"4.00","nrml_multiplier":"1"},{"tradingsymbol":"AJANTA PHARMA LIMITED","mis_multiplier":"5.00","nrml_multiplier":"1"},{"tradingsymbol":"AKZO NOBEL INDIA LIMITED","mis_multiplier":"5.00","nrml_multiplier":"1"},{"tradingsymbol":"ALEMBIC LIMITED","mis_multiplier":"2.00","nrml_multiplier":"1"},{"tradingsymbol":"ALEMBIC PHARMA LTD","mis_multiplier":"5.00","nrml_multiplier":"1"},{"tradingsymbol":"ALKEM LABORATORIES LTD.","mis_multiplier":"4.00","nrml_multiplier":"1"},{"tradingsymbol":"ALLCARGO LOGISTICS LTD","mis_multiplier":"3.00","nrml_multiplier":"1"},{"tradingsymbol":"AMARA RAJA BATTERIES LTD.","mis_multiplier":"10.00","nrml_multiplier":"1"},{"tradingsymbol":"AMBUJA CEMENTS LTD","mis_multiplier":"10.00","nrml_multiplier":"1"},{"tradingsymbol":"AMRUTANJAN HEALTH CARE LTD.","mis_multiplier":"2.00","nrml_multiplier":"1"},{"tradingsymbol":"ANANT RAJ LIMITED","mis_multiplier":"2.00","nrml_multiplier":"1"},{"tradingsymbol":"ANDHRA PAPER LIMITED","mis_multiplier":"1.00","nrml_multiplier":"1"},{"tradingsymbol":"APL APOLLO TUBES LTD.","mis_multiplier":"2.00","nrml_multiplier":"1"},{"tradingsymbol":"APOLLO HOSPITALS ENTER. L","mis_multiplier":"8.00","nrml_multiplier":"1"},{"tradingsymbol":"Apollo Pipes Limited","mis_multiplier":"2.50","nrml_multiplier":"1"},{"tradingsymbol":"APOLLO TYRES LTD","mis_multiplier":"6.67","nrml_multiplier":"1"},{"tradingsymbol":"APTECH LIMITED","mis_multiplier":"3.00","nrml_multiplier":"1"},{"tradingsymbol":"ARVIND LIMITED","mis_multiplier":"8.00","nrml_multiplier":"1"},{"tradingsymbol":"ASAHI INDIA GLASS LIMITED","mis_multiplier":"3.00","nrml_multiplier":"1"},{"tradingsymbol":"ASHOK LEYLAND LTD","mis_multiplier":"6.67","nrml_multiplier":"1"},{"tradingsymbol":"ASIAN PAINTS LIMITED","mis_multiplier":"12.00","nrml_multiplier":"1"},{"tradingsymbol":"Aster DM Healthcare Limited","mis_multiplier":"1.00","nrml_multiplier":"1"},{"tradingsymbol":"ASTRA MICROWAVE LTD","mis_multiplier":"3.00","nrml_multiplier":"1"},{"tradingsymbol":"ASTRAL POLY TECHNIK LTD.","mis_multiplier":"2.50","nrml_multiplier":"1"},{"tradingsymbol":"ASTRAZENECA PHARMA IND LT","mis_multiplier":"4.00","nrml_multiplier":"1"},{"tradingsymbol":"ATUL AUTO LTD","mis_multiplier":"2.00","nrml_multiplier":"1"},{"tradingsymbol":"ATUL LTD","mis_multiplier":"5.00","nrml_multiplier":"1"},{"tradingsymbol":"AU Small Finance Bank Ltd","mis_multiplier":"5.00","nrml_multiplier":"1"},{"tradingsymbol":"AUROBINDO PHARMA LTD","mis_multiplier":"6.00","nrml_multiplier":"1"},{"tradingsymbol":"AUTOLINE INDUSTRIES LTD","mis_multiplier":"2.00","nrml_multiplier":"1"},{"tradingsymbol":"AUTOMOTIVE AXLES LIMITED","mis_multiplier":"3.00","nrml_multiplier":"1"},{"tradingsymbol":"AVANTI FEEDS LTD.","mis_multiplier":"4.00","nrml_multiplier":"1"},{"tradingsymbol":"AXIS BANK LIMITED","mis_multiplier":"7.00","nrml_multiplier":"1"},{"tradingsymbol":"BAJAJ AUTO LIMITED","mis_multiplier":"10.00","nrml_multiplier":"1"},{"tradingsymbol":"BAJAJ CORP LIMITED","mis_multiplier":"5.00","nrml_multiplier":"1"},{"tradingsymbol":"BAJAJ ELECT.LTD","mis_multiplier":"5.00","nrml_multiplier":"1"},{"tradingsymbol":"BAJAJ FINANCE LIMITED","mis_multiplier":"8.00","nrml_multiplier":"1"},{"tradingsymbol":"BAJAJ FINSERV LTD.","mis_multiplier":"8.00","nrml_multiplier":"1"},{"tradingsymbol":"BAJAJ HINDUSTHAN SUGAR LT","mis_multiplier":"3.00","nrml_multiplier":"1"},{"tradingsymbol":"BAJAJ HOLDINGS & INVS LTD","mis_multiplier":"4.00","nrml_multiplier":"1"},{"tradingsymbol":"BALAJI TELEFILMS LIMITED.","mis_multiplier":"1.00","nrml_multiplier":"1"},{"tradingsymbol":"BALKRISHNA IND. LTD","mis_multiplier":"6.67","nrml_multiplier":"1"},{"tradingsymbol":"BALLARPUR INDUSTRIES LTD","mis_multiplier":"2.00","nrml_multiplier":"1"},{"tradingsymbol":"BALMER LAWRIE & CO LTD","mis_multiplier":"3.00","nrml_multiplier":"1"},{"tradingsymbol":"BALRAMPUR CHINI MILLS LTD","mis_multiplier":"3.00","nrml_multiplier":"1"},{"tradingsymbol":"BANCO PRODUCTS (I) LTD","mis_multiplier":"3.00","nrml_multiplier":"1"},{"tradingsymbol":"Bandhan Bank Limited","mis_multiplier":"5.00","nrml_multiplier":"1"},{"tradingsymbol":"BANK OF BARODA","mis_multiplier":"5.00","nrml_multiplier":"1"},{"tradingsymbol":"BANK OF INDIA","mis_multiplier":"5.00","nrml_multiplier":"1"},{"tradingsymbol":"BANK OF MAHARASHTRA","mis_multiplier":"3.00","nrml_multiplier":"1"},{"tradingsymbol":"BASF INDIA LTD","mis_multiplier":"3.00","nrml_multiplier":"1"},{"tradingsymbol":"BATA INDIA LTD","mis_multiplier":"8.00","nrml_multiplier":"1"},{"tradingsymbol":"BAYER CROPSCIENCE LTD","mis_multiplier":"5.00","nrml_multiplier":"1"},{"tradingsymbol":"BEML LIMITED","mis_multiplier":"3.00","nrml_multiplier":"1"},{"tradingsymbol":"BERGER PAINTS (I) LTD","mis_multiplier":"8.00","nrml_multiplier":"1"},{"tradingsymbol":"BF UTILITIES LIMITED","mis_multiplier":"3.00","nrml_multiplier":"1"},{"tradingsymbol":"BGR ENERGY SYSTEMS LTD","mis_multiplier":"3.00","nrml_multiplier":"1"},{"tradingsymbol":"BHARAT BIJLEE LTD","mis_multiplier":"1.00","nrml_multiplier":"1"},{"tradingsymbol":"BHARAT ELECTRONICS LTD","mis_multiplier":"3.00","nrml_multiplier":"1"},{"tradingsymbol":"BHARAT FORGE LTD","mis_multiplier":"8.00","nrml_multiplier":"1"},{"tradingsymbol":"BHARAT PETROLEUM CORP  LT","mis_multiplier":"5.00","nrml_multiplier":"1"},{"tradingsymbol":"BHARTI AIRTEL LIMITED","mis_multiplier":"10.00","nrml_multiplier":"1"},{"tradingsymbol":"BHARTI INFRATEL LTD.","mis_multiplier":"5.00","nrml_multiplier":"1"},{"tradingsymbol":"BHEL","mis_multiplier":"5.00","nrml_multiplier":"1"},{"tradingsymbol":"BIOCON LIMITED.","mis_multiplier":"5.00","nrml_multiplier":"1"},{"tradingsymbol":"BIRLA CORPORATION LTD","mis_multiplier":"2.00","nrml_multiplier":"1"},{"tradingsymbol":"BLISS GVS PHARMA LTD.","mis_multiplier":"1.00","nrml_multiplier":"1"},{"tradingsymbol":"BLUE DART EXPRESS LTD","mis_multiplier":"5.00","nrml_multiplier":"1"},{"tradingsymbol":"BLUE STAR LIMITED","mis_multiplier":"3.00","nrml_multiplier":"1"},{"tradingsymbol":"BOMBAY BURMAH TRADING COR","mis_multiplier":"3.00","nrml_multiplier":"1"},{"tradingsymbol":"BOSCH LIMITED","mis_multiplier":"6.67","nrml_multiplier":"1"},{"tradingsymbol":"BRIGADE ENTERPRISES LTD.","mis_multiplier":"2.00","nrml_multiplier":"1"},{"tradingsymbol":"BRITANNIA INDUSTRIES LTD","mis_multiplier":"8.00","nrml_multiplier":"1"},{"tradingsymbol":"BSE LIMITED","mis_multiplier":"2.00","nrml_multiplier":"1"},{"tradingsymbol":"CADILA HEALTHCARE LIMITED","mis_multiplier":"8.00","nrml_multiplier":"1"},{"tradingsymbol":"CAN FIN HOMES LTD","mis_multiplier":"4.00","nrml_multiplier":"1"},{"tradingsymbol":"CANARA BANK","mis_multiplier":"5.00","nrml_multiplier":"1"},{"tradingsymbol":"Capacit'e Infraprojects Limited","mis_multiplier":"2.00","nrml_multiplier":"1"},{"tradingsymbol":"CAPLIN POINT LABORATORIES LTD.","mis_multiplier":"2.00","nrml_multiplier":"1"},{"tradingsymbol":"CARBORUNDUM UNIVERSAL LTD","mis_multiplier":"4.00","nrml_multiplier":"1"},{"tradingsymbol":"CARE LIMITED","mis_multiplier":"5.00","nrml_multiplier":"1"},{"tradingsymbol":"CASTROL INDIA LIMITED","mis_multiplier":"8.00","nrml_multiplier":"1"},{"tradingsymbol":"CCL PRODUCTS (I) LTD","mis_multiplier":"3.00","nrml_multiplier":"1"},{"tradingsymbol":"CEAT LIMITED","mis_multiplier":"5.00","nrml_multiplier":"1"},{"tradingsymbol":"CENTRAL BANK OF INDIA","mis_multiplier":"3.00","nrml_multiplier":"1"},{"tradingsymbol":"CENTRAL DEPOSITORY SERVICES (INDIA) LIMITED","mis_multiplier":"3.00","nrml_multiplier":"1"},{"tradingsymbol":"CENTRUM CAPITAL LTD.","mis_multiplier":"2.00","nrml_multiplier":"1"},{"tradingsymbol":"CENTURY PLYBOARDS (I) LTD","mis_multiplier":"1.00","nrml_multiplier":"1"},{"tradingsymbol":"CENTURY TEXTILES LTD","mis_multiplier":"5.00","nrml_multiplier":"1"},{"tradingsymbol":"CERA SANITARYWARE LTD","mis_multiplier":"3.00","nrml_multiplier":"1"},{"tradingsymbol":"CESC LTD","mis_multiplier":"5.00","nrml_multiplier":"1"},{"tradingsymbol":"CGPOWER","mis_multiplier":"5.00","nrml_multiplier":"1"},{"tradingsymbol":"CHAMBAL FERTILIZERS LTD","mis_multiplier":"5.00","nrml_multiplier":"1"},{"tradingsymbol":"Chemcon Speciality Chemicals Limited","mis_multiplier":"2.00","nrml_multiplier":"1"},{"tradingsymbol":"CHENNAI PETROLEUM CORP LT","mis_multiplier":"2.00","nrml_multiplier":"1"},{"tradingsymbol":"Cholamandalam Financial Holdings Ltd","mis_multiplier":"2.86","nrml_multiplier":"1"},{"tradingsymbol":"CHOLAMANDALAM IN & FIN CO","mis_multiplier":"5.00","nrml_multiplier":"1"},{"tradingsymbol":"CIPLA LTD","mis_multiplier":"10.00","nrml_multiplier":"1"},{"tradingsymbol":"CITY UNION BANK LTD","mis_multiplier":"4.00","nrml_multiplier":"1"},{"tradingsymbol":"CLARIANT CHEMICALS (INDIA","mis_multiplier":"3.00","nrml_multiplier":"1"},{"tradingsymbol":"COAL INDIA LTD","mis_multiplier":"8.00","nrml_multiplier":"1"},{"tradingsymbol":"Cochin Shipyard Ltd","mis_multiplier":"2.00","nrml_multiplier":"1"},{"tradingsymbol":"COLGATE PALMOLIVE LTD.","mis_multiplier":"10.00","nrml_multiplier":"1"},{"tradingsymbol":"Computer Age Management Services Limited","mis_multiplier":"2.00","nrml_multiplier":"1"},{"tradingsymbol":"CONTAINER CORP OF IND LTD","mis_multiplier":"5.00","nrml_multiplier":"1"},{"tradingsymbol":"COROMANDEL INTERNTL. LTD","mis_multiplier":"4.00","nrml_multiplier":"1"},{"tradingsymbol":"CreditAccess Grameen Limited","mis_multiplier":"2.50","nrml_multiplier":"1"},{"tradingsymbol":"CRISIL LTD","mis_multiplier":"5.00","nrml_multiplier":"1"},{"tradingsymbol":"Crompton Greaves Consumer Elec","mis_multiplier":"4.00","nrml_multiplier":"1"},{"tradingsymbol":"CSB Bank Limited","mis_multiplier":"2.00","nrml_multiplier":"1"},{"tradingsymbol":"CUMMINS INDIA LTD","mis_multiplier":"6.67","nrml_multiplier":"1"},{"tradingsymbol":"CYIENT LIMITED","mis_multiplier":"4.00","nrml_multiplier":"1"},{"tradingsymbol":"D B REALTY LIMITED","mis_multiplier":"3.00","nrml_multiplier":"1"},{"tradingsymbol":"D.B.CORP LTD","mis_multiplier":"3.00","nrml_multiplier":"1"},{"tradingsymbol":"DABUR INDIA LTD","mis_multiplier":"10.00","nrml_multiplier":"1"},{"tradingsymbol":"DCB BANK LIMITED","mis_multiplier":"4.00","nrml_multiplier":"1"},{"tradingsymbol":"DCM SHRIRAM LIMITED","mis_multiplier":"2.00","nrml_multiplier":"1"},{"tradingsymbol":"DEEPAK FERTILIZERS & PETR","mis_multiplier":"3.00","nrml_multiplier":"1"},{"tradingsymbol":"DEEPAK NITRITE LTD.","mis_multiplier":"3.00","nrml_multiplier":"1"},{"tradingsymbol":"DELTA CORP LIMITED","mis_multiplier":"3.00","nrml_multiplier":"1"},{"tradingsymbol":"DEN NETWORKS LTD","mis_multiplier":"2.00","nrml_multiplier":"1"},{"tradingsymbol":"DFM FOODS LTD.","mis_multiplier":"2.00","nrml_multiplier":"1"},{"tradingsymbol":"DHANLAXMI BANK LIMITED","mis_multiplier":"2.00","nrml_multiplier":"1"},{"tradingsymbol":"DHANUKA AGRITECH LTD.","mis_multiplier":"4.00","nrml_multiplier":"1"},{"tradingsymbol":"Dilip Buildcon Ltd","mis_multiplier":"2.00","nrml_multiplier":"1"},{"tradingsymbol":"DISH TV INDIA LTD.","mis_multiplier":"2.00","nrml_multiplier":"1"},{"tradingsymbol":"DIVI'S LABORATORIES LTD","mis_multiplier":"6.67","nrml_multiplier":"1"},{"tradingsymbol":"Dixon Technologies (India) Limited","mis_multiplier":"2.00","nrml_multiplier":"1"},{"tradingsymbol":"DLF LIMITED","mis_multiplier":"5.00","nrml_multiplier":"1"},{"tradingsymbol":"DR. LAL PATH LABS LTD.","mis_multiplier":"5.00","nrml_multiplier":"1"},{"tradingsymbol":"DR. REDDY'S LABORATORIES","mis_multiplier":"10.00","nrml_multiplier":"1"},{"tradingsymbol":"DREDGING CORP OF INDIA","mis_multiplier":"1.00","nrml_multiplier":"1"},{"tradingsymbol":"ECLERX SERVICES LTD","mis_multiplier":"4.00","nrml_multiplier":"1"},{"tradingsymbol":"EDELWEISS FIN SERV LTD","mis_multiplier":"3.00","nrml_multiplier":"1"},{"tradingsymbol":"EICHER MOTORS LTD","mis_multiplier":"8.00","nrml_multiplier":"1"},{"tradingsymbol":"EID PARRY INDIA LTD","mis_multiplier":"2.00","nrml_multiplier":"1"},{"tradingsymbol":"EIH LIMITED","mis_multiplier":"2.00","nrml_multiplier":"1"},{"tradingsymbol":"EMAMI LIMITED","mis_multiplier":"5.00","nrml_multiplier":"1"},{"tradingsymbol":"Endurance Technologies Limited","mis_multiplier":"4.00","nrml_multiplier":"1"},{"tradingsymbol":"ENGINEERS INDIA LTD","mis_multiplier":"3.00","nrml_multiplier":"1"},{"tradingsymbol":"ENTERTAIN NET. IND. LTD.","mis_multiplier":"2.00","nrml_multiplier":"1"},{"tradingsymbol":"Equitas Holdings Limited","mis_multiplier":"3.00","nrml_multiplier":"1"},{"tradingsymbol":"Equitas Small Finance Bank Ltd","mis_multiplier":"3.00","nrml_multiplier":"1"},{"tradingsymbol":"Eris Lifesciences Limited","mis_multiplier":"2.50","nrml_multiplier":"1"},{"tradingsymbol":"EROS INTL MEDIA LTD","mis_multiplier":"1.00","nrml_multiplier":"1"},{"tradingsymbol":"ESAB INDIA LTD.","mis_multiplier":"2.50","nrml_multiplier":"1"},{"tradingsymbol":"ESCORTS INDIA LTD","mis_multiplier":"5.00","nrml_multiplier":"1"},{"tradingsymbol":"EXIDE INDUSTRIES LTD","mis_multiplier":"6.67","nrml_multiplier":"1"},{"tradingsymbol":"FDC LIMITED","mis_multiplier":"4.00","nrml_multiplier":"1"},{"tradingsymbol":"FEDERAL BANK LTD","mis_multiplier":"5.00","nrml_multiplier":"1"},{"tradingsymbol":"FIEM INDUSTRIES LTD.","mis_multiplier":"1.00","nrml_multiplier":"1"},{"tradingsymbol":"Fine Organic Industries Limite","mis_multiplier":"4.00","nrml_multiplier":"1"},{"tradingsymbol":"FINOLEX CABLES LTD","mis_multiplier":"4.00","nrml_multiplier":"1"},{"tradingsymbol":"FINOLEX INDUSTRIES LTD.","mis_multiplier":"2.00","nrml_multiplier":"1"},{"tradingsymbol":"FIRSTSOURCE SOLU. LTD.","mis_multiplier":"2.00","nrml_multiplier":"1"},{"tradingsymbol":"FORCE MOTORS LTD.","mis_multiplier":"2.00","nrml_multiplier":"1"},{"tradingsymbol":"FORTIS HEALTHCARE LTD","mis_multiplier":"4.00","nrml_multiplier":"1"},{"tradingsymbol":"FUTURE CONSUMER LIMITED","mis_multiplier":"2.00","nrml_multiplier":"1"},{"tradingsymbol":"FUTURE ENTERPRISES LTD","mis_multiplier":"2.00","nrml_multiplier":"1"},{"tradingsymbol":"FUTURE LIFESTYLE FASHIONS LTD","mis_multiplier":"2.00","nrml_multiplier":"1"},{"tradingsymbol":"Future Retail Ltd.","mis_multiplier":"2.00","nrml_multiplier":"1"},{"tradingsymbol":"Future Supply Chain Solutions Limited","mis_multiplier":"2.00","nrml_multiplier":"1"},{"tradingsymbol":"GABRIEL INDIA LTD.","mis_multiplier":"2.00","nrml_multiplier":"1"},{"tradingsymbol":"GAIL (INDIA) LTD","mis_multiplier":"5.00","nrml_multiplier":"1"},{"tradingsymbol":"Galaxy Surfactants Limited","mis_multiplier":"4.00","nrml_multiplier":"1"},{"tradingsymbol":"GATEWAY DISTRIPARKS LTD.","mis_multiplier":"1.00","nrml_multiplier":"1"},{"tradingsymbol":"GATI LIMITED","mis_multiplier":"2.00","nrml_multiplier":"1"},{"tradingsymbol":"GE Power India Ltd","mis_multiplier":"2.00","nrml_multiplier":"1"},{"tradingsymbol":"GE T&D INDIA LIMITED","mis_multiplier":"5.00","nrml_multiplier":"1"},{"tradingsymbol":"General Insurance Corporation of India","mis_multiplier":"5.00","nrml_multiplier":"1"},{"tradingsymbol":"GHCL LIMITED","mis_multiplier":"1.00","nrml_multiplier":"1"},{"tradingsymbol":"GIC HOUSING FINANCE LTD","mis_multiplier":"2.00","nrml_multiplier":"1"},{"tradingsymbol":"GILLETTE INDIA LTD","mis_multiplier":"5.00","nrml_multiplier":"1"},{"tradingsymbol":"Gland Pharma Limited","mis_multiplier":"1.00","nrml_multiplier":"1"},{"tradingsymbol":"GLAXOSMITHKLINE CONSUMER","mis_multiplier":"10.00","nrml_multiplier":"1"},{"tradingsymbol":"GLAXOSMITHKLINE PHARMA LT","mis_multiplier":"10.00","nrml_multiplier":"1"},{"tradingsymbol":"GLENMARK PHARMACEUTICALS","mis_multiplier":"8.00","nrml_multiplier":"1"},{"tradingsymbol":"GMM PFAUDLER LTD","mis_multiplier":"1.00","nrml_multiplier":"1"},{"tradingsymbol":"GMR INFRASTRUCTURE LTD.","mis_multiplier":"4.00","nrml_multiplier":"1"},{"tradingsymbol":"GODFREY PHILLIPS INDIA LT","mis_multiplier":"2.00","nrml_multiplier":"1"},{"tradingsymbol":"Godrej Agrovet Limited","mis_multiplier":"5.00","nrml_multiplier":"1"},{"tradingsymbol":"GODREJ CONSUMER PRODUCTS","mis_multiplier":"8.00","nrml_multiplier":"1"},{"tradingsymbol":"GODREJ INDUSTRIES LTD","mis_multiplier":"5.00","nrml_multiplier":"1"},{"tradingsymbol":"GODREJ PROPERTIES LTD","mis_multiplier":"8.00","nrml_multiplier":"1"},{"tradingsymbol":"GRANULES INDIA LIMITED","mis_multiplier":"2.00","nrml_multiplier":"1"},{"tradingsymbol":"GRAPHITE INDIA LTD.","mis_multiplier":"2.00","nrml_multiplier":"1"},{"tradingsymbol":"GRASIM INDUSTRIES LTD","mis_multiplier":"8.00","nrml_multiplier":"1"},{"tradingsymbol":"GREAVES COTTON LTD.","mis_multiplier":"1.00","nrml_multiplier":"1"},{"tradingsymbol":"GREENPLY INDUSTRIES LTD.","mis_multiplier":"2.00","nrml_multiplier":"1"},{"tradingsymbol":"GRINDWELL NORTON LTD.","mis_multiplier":"2.00","nrml_multiplier":"1"},{"tradingsymbol":"GUJ NAR VAL FER & CHEM L","mis_multiplier":"2.00","nrml_multiplier":"1"},{"tradingsymbol":"GUJ STATE FERT & CHEM LTD","mis_multiplier":"3.00","nrml_multiplier":"1"},{"tradingsymbol":"GUJARAT ALKALIES & CHEM","mis_multiplier":"3.00","nrml_multiplier":"1"},{"tradingsymbol":"GUJARAT FLUOROCHEMICALS L","mis_multiplier":"3.00","nrml_multiplier":"1"},{"tradingsymbol":"Gujarat Gas Ltd","mis_multiplier":"2.00","nrml_multiplier":"1"},{"tradingsymbol":"GUJARAT MINERAL DEV CORP","mis_multiplier":"2.00","nrml_multiplier":"1"},{"tradingsymbol":"GUJARAT PIPAVAV PORT LTD","mis_multiplier":"3.00","nrml_multiplier":"1"},{"tradingsymbol":"GUJARAT STATE PETRO LTD","mis_multiplier":"3.00","nrml_multiplier":"1"},{"tradingsymbol":"GULF OIL LUB. IND. LTD.","mis_multiplier":"2.00","nrml_multiplier":"1"},{"tradingsymbol":"Happiest Minds Technologies Ltd","mis_multiplier":"2.00","nrml_multiplier":"1"},{"tradingsymbol":"HATHWAY CABLE & DATACOM","mis_multiplier":"2.00","nrml_multiplier":"1"},{"tradingsymbol":"HAVELLS INDIA LIMITED","mis_multiplier":"8.00","nrml_multiplier":"1"},{"tradingsymbol":"HAWKINS COOKERS LTD","mis_multiplier":"5.00","nrml_multiplier":"1"},{"tradingsymbol":"HCL INFOSYSTEMS LTD","mis_multiplier":"2.00","nrml_multiplier":"1"},{"tradingsymbol":"HCL TECHNOLOGIES LTD","mis_multiplier":"10.00","nrml_multiplier":"1"},{"tradingsymbol":"HDFC Asset Management Company Limited","mis_multiplier":"5.00","nrml_multiplier":"1"},{"tradingsymbol":"HDFC BANK LTD","mis_multiplier":"10.00","nrml_multiplier":"1"},{"tradingsymbol":"HDFC LTD","mis_multiplier":"10.00","nrml_multiplier":"1"},{"tradingsymbol":"HDFC Standard Life Insurance Company Limited","mis_multiplier":"6.67","nrml_multiplier":"1"},{"tradingsymbol":"HEALTHCARE GLOB. ENT. LTD","mis_multiplier":"1.00","nrml_multiplier":"1"},{"tradingsymbol":"HEG LTD","mis_multiplier":"2.00","nrml_multiplier":"1"},{"tradingsymbol":"HEIDELBERGCEMENT (I) LTD","mis_multiplier":"2.00","nrml_multiplier":"1"},{"tradingsymbol":"HERO MOTOCORP LIMITED","mis_multiplier":"10.00","nrml_multiplier":"1"},{"tradingsymbol":"HEXAWARE TECHNOLOGIES LTD","mis_multiplier":"5.00","nrml_multiplier":"1"},{"tradingsymbol":"HIMACHAL FUT COM LTD","mis_multiplier":"2.00","nrml_multiplier":"1"},{"tradingsymbol":"Himadri Speciality Chemical Ltd","mis_multiplier":"1.00","nrml_multiplier":"1"},{"tradingsymbol":"HIMATSINGKA SEIDE LTD","mis_multiplier":"2.00","nrml_multiplier":"1"},{"tradingsymbol":"HINDALCO  INDUSTRIES  LTD","mis_multiplier":"7.00","nrml_multiplier":"1"},{"tradingsymbol":"HINDUJA GLOBAL SOLS. LTD.","mis_multiplier":"2.00","nrml_multiplier":"1"},{"tradingsymbol":"HINDUSTAN CONSTRUCTION CO","mis_multiplier":"2.00","nrml_multiplier":"1"},{"tradingsymbol":"HINDUSTAN COPPER LTD","mis_multiplier":"3.00","nrml_multiplier":"1"},{"tradingsymbol":"HINDUSTAN MOTORS LIMITED","mis_multiplier":"1.00","nrml_multiplier":"1"},{"tradingsymbol":"HINDUSTAN OIL EXPLORATION","mis_multiplier":"1.00","nrml_multiplier":"1"},{"tradingsymbol":"HINDUSTAN PETROLEUM CORP","mis_multiplier":"7.00","nrml_multiplier":"1"},{"tradingsymbol":"HINDUSTAN UNILEVER LTD.","mis_multiplier":"12.00","nrml_multiplier":"1"},{"tradingsymbol":"HINDUSTAN ZINC LIMITED","mis_multiplier":"8.00","nrml_multiplier":"1"},{"tradingsymbol":"HONEYWELL AUTOMATION IND","mis_multiplier":"4.00","nrml_multiplier":"1"},{"tradingsymbol":"Housing and Urban Development Corporation Ltd","mis_multiplier":"4.00","nrml_multiplier":"1"},{"tradingsymbol":"HSIL LIMITED","mis_multiplier":"2.00","nrml_multiplier":"1"},{"tradingsymbol":"ICICI BANK LTD.","mis_multiplier":"7.00","nrml_multiplier":"1"},{"tradingsymbol":"ICICI Lombard General Insurance Company Limited","mis_multiplier":"6.67","nrml_multiplier":"1"},{"tradingsymbol":"ICICI Prudential Life Insuranc","mis_multiplier":"6.67","nrml_multiplier":"1"},{"tradingsymbol":"ICICI Securities Limited","mis_multiplier":"3.00","nrml_multiplier":"1"},{"tradingsymbol":"ICRA LIMITED","mis_multiplier":"4.00","nrml_multiplier":"1"},{"tradingsymbol":"IDBI BANK LIMITED","mis_multiplier":"5.00","nrml_multiplier":"1"},{"tradingsymbol":"IDEA CELLULAR LIMITED","mis_multiplier":"2.50","nrml_multiplier":"1"},{"tradingsymbol":"IDFC BANK LIMITED","mis_multiplier":"5.00","nrml_multiplier":"1"},{"tradingsymbol":"IDFC LIMITED","mis_multiplier":"8.00","nrml_multiplier":"1"},{"tradingsymbol":"IFB INDUSTRIES LTD","mis_multiplier":"1.00","nrml_multiplier":"1"},{"tradingsymbol":"IFCI LTD","mis_multiplier":"5.00","nrml_multiplier":"1"},{"tradingsymbol":"IGARASHI MOTORS INDIA LTD","mis_multiplier":"1.00","nrml_multiplier":"1"},{"tradingsymbol":"IIFL HOLDINGS LIMITED","mis_multiplier":"5.00","nrml_multiplier":"1"},{"tradingsymbol":"IIFL Wealth Management Limited","mis_multiplier":"2.00","nrml_multiplier":"1"},{"tradingsymbol":"INDIABULLS HSG FIN LTD","mis_multiplier":"4.00","nrml_multiplier":"1"},{"tradingsymbol":"INDIABULLS REAL EST. LTD","mis_multiplier":"3.00","nrml_multiplier":"1"},{"tradingsymbol":"INDIAN BANK","mis_multiplier":"3.00","nrml_multiplier":"1"},{"tradingsymbol":"Indian Energy Exchange Limited","mis_multiplier":"5.00","nrml_multiplier":"1"},{"tradingsymbol":"INDIAN OIL CORP LTD","mis_multiplier":"6.67","nrml_multiplier":"1"},{"tradingsymbol":"INDIAN OVERSEAS BANK","mis_multiplier":"5.00","nrml_multiplier":"1"},{"tradingsymbol":"Indian Railway Catering And Tourism Corporation Limited","mis_multiplier":"3.00","nrml_multiplier":"1"},{"tradingsymbol":"INDO COUNT INDUSTRIES LTD","mis_multiplier":"2.00","nrml_multiplier":"1"},{"tradingsymbol":"INDOCO REMEDIES LTD.","mis_multiplier":"2.00","nrml_multiplier":"1"},{"tradingsymbol":"IndoStar Capital Finance Limited","mis_multiplier":"5.00","nrml_multiplier":"1"},{"tradingsymbol":"INDRAPRASTHA GAS LTD","mis_multiplier":"8.00","nrml_multiplier":"1"},{"tradingsymbol":"INDUSIND BANK LIMITED","mis_multiplier":"5.00","nrml_multiplier":"1"},{"tradingsymbol":"INFIBEAM INCORP. LIMITED","mis_multiplier":"1.00","nrml_multiplier":"1"},{"tradingsymbol":"INFO EDGE (I) LTD","mis_multiplier":"5.00","nrml_multiplier":"1"},{"tradingsymbol":"INFOSYS LIMITED","mis_multiplier":"8.00","nrml_multiplier":"1"},{"tradingsymbol":"INGERSOLL-RAND INDIA LTD","mis_multiplier":"3.00","nrml_multiplier":"1"},{"tradingsymbol":"INOX LEISURE LIMITED","mis_multiplier":"3.00","nrml_multiplier":"1"},{"tradingsymbol":"INOX WIND LIMITED","mis_multiplier":"2.00","nrml_multiplier":"1"},{"tradingsymbol":"INTELLECT DESIGN ARENA","mis_multiplier":"1.00","nrml_multiplier":"1"},{"tradingsymbol":"INTERGLOBE AVIATION LTD","mis_multiplier":"5.00","nrml_multiplier":"1"},{"tradingsymbol":"IPCA LABORATORIES LTD","mis_multiplier":"3.00","nrml_multiplier":"1"},{"tradingsymbol":"IRB INFRA DEV LTD.","mis_multiplier":"3.00","nrml_multiplier":"1"},{"tradingsymbol":"IRCON International Limited","mis_multiplier":"1.00","nrml_multiplier":"1"},{"tradingsymbol":"ITC LTD","mis_multiplier":"12.00","nrml_multiplier":"1"},{"tradingsymbol":"ITD CEMENTATION INDIA LTD.","mis_multiplier":"2.00","nrml_multiplier":"1"},{"tradingsymbol":"J & K BANK LTD.","mis_multiplier":"3.00","nrml_multiplier":"1"},{"tradingsymbol":"J B CHEMICALS AND PHARMA","mis_multiplier":"2.00","nrml_multiplier":"1"},{"tradingsymbol":"JAGRAN PRAKASHAN LIMITED","mis_multiplier":"2.00","nrml_multiplier":"1"},{"tradingsymbol":"JAI CORP LIMITED","mis_multiplier":"2.00","nrml_multiplier":"1"},{"tradingsymbol":"JAIN IRRIGATION SYSTEMS","mis_multiplier":"2.00","nrml_multiplier":"1"},{"tradingsymbol":"JAIPRAKASH ASSOCIATES LTD","mis_multiplier":"3.00","nrml_multiplier":"1"},{"tradingsymbol":"JAMNA AUTO INDUSTRIES LTD.","mis_multiplier":"2.00","nrml_multiplier":"1"},{"tradingsymbol":"JINDAL SAW LIMITED","mis_multiplier":"2.00","nrml_multiplier":"1"},{"tradingsymbol":"JINDAL STEEL & POWER LTD","mis_multiplier":"5.00","nrml_multiplier":"1"},{"tradingsymbol":"JK CEMENT LIMITED","mis_multiplier":"3.00","nrml_multiplier":"1"},{"tradingsymbol":"JK LAKSHMI CEMENT LTD","mis_multiplier":"3.00","nrml_multiplier":"1"},{"tradingsymbol":"JK PAPER LTD","mis_multiplier":"2.50","nrml_multiplier":"1"},{"tradingsymbol":"JK TYRE & INDUSTRIES LTD","mis_multiplier":"3.00","nrml_multiplier":"1"},{"tradingsymbol":"JM FINANCIAL LIMITED","mis_multiplier":"5.00","nrml_multiplier":"1"},{"tradingsymbol":"JMT AUTO LTD.","mis_multiplier":"2.00","nrml_multiplier":"1"},{"tradingsymbol":"JOHNSON CONTROLS HITACHI","mis_multiplier":"1.00","nrml_multiplier":"1"},{"tradingsymbol":"JSW ENERGY LIMITED","mis_multiplier":"5.00","nrml_multiplier":"1"},{"tradingsymbol":"JSW STEEL LIMITED","mis_multiplier":"8.00","nrml_multiplier":"1"},{"tradingsymbol":"JUBILANT FOODWORKS LTD","mis_multiplier":"7.00","nrml_multiplier":"1"},{"tradingsymbol":"JUBILANT INDUSTRIES LTD","mis_multiplier":"2.00","nrml_multiplier":"1"},{"tradingsymbol":"JUBILANT LIFE SCIENCE LTD","mis_multiplier":"2.00","nrml_multiplier":"1"},{"tradingsymbol":"JUSTDIAL LTD.","mis_multiplier":"3.00","nrml_multiplier":"1"},{"tradingsymbol":"JYOTHY LABS LTD","mis_multiplier":"3.00","nrml_multiplier":"1"},{"tradingsymbol":"K.P.R.MILL LTD.","mis_multiplier":"2.00","nrml_multiplier":"1"},{"tradingsymbol":"KAJARIA CERAMICS LTD","mis_multiplier":"5.00","nrml_multiplier":"1"},{"tradingsymbol":"KALPATARU POWER TRANS. LT","mis_multiplier":"2.00","nrml_multiplier":"1"},{"tradingsymbol":"KANSAI NEROLAC PAINTS LTD","mis_multiplier":"5.00","nrml_multiplier":"1"},{"tradingsymbol":"KARNATAKA BANK LIMITED","mis_multiplier":"3.00","nrml_multiplier":"1"},{"tradingsymbol":"KARUR VYSYA BANK LTD","mis_multiplier":"4.00","nrml_multiplier":"1"},{"tradingsymbol":"KAVERI SEED CO. LTD.","mis_multiplier":"3.00","nrml_multiplier":"1"},{"tradingsymbol":"KEC INTL. LIMITED","mis_multiplier":"3.00","nrml_multiplier":"1"},{"tradingsymbol":"KEI INDUSTRIES LTD","mis_multiplier":"2.00","nrml_multiplier":"1"},{"tradingsymbol":"KESORAM INDUSTRIES LTD","mis_multiplier":"1.00","nrml_multiplier":"1"},{"tradingsymbol":"Khadim India Limited","mis_multiplier":"2.00","nrml_multiplier":"1"},{"tradingsymbol":"KIRLOSKAR OIL ENGINES LTD.","mis_multiplier":"2.00","nrml_multiplier":"1"},{"tradingsymbol":"KITEX GARMENTS LTD","mis_multiplier":"1.00","nrml_multiplier":"1"},{"tradingsymbol":"KNR CONSTRU LTD.","mis_multiplier":"1.00","nrml_multiplier":"1"},{"tradingsymbol":"KOKUYO CAMLIN LIMITED","mis_multiplier":"1.00","nrml_multiplier":"1"},{"tradingsymbol":"KOLTE PATIL DEV. LTD.","mis_multiplier":"1.00","nrml_multiplier":"1"},{"tradingsymbol":"KOTAK MAHINDRA BANK LTD","mis_multiplier":"7.00","nrml_multiplier":"1"},{"tradingsymbol":"KPIT TECHNOLOGIES LTD","mis_multiplier":"3.00","nrml_multiplier":"1"},{"tradingsymbol":"KRBL LIMITED","mis_multiplier":"2.00","nrml_multiplier":"1"},{"tradingsymbol":"L&T FINANCE HOLDINGS LTD","mis_multiplier":"5.00","nrml_multiplier":"1"},{"tradingsymbol":"L&T Technology Services Limite","mis_multiplier":"5.00","nrml_multiplier":"1"},{"tradingsymbol":"LA OPALA RG LIMITED","mis_multiplier":"4.00","nrml_multiplier":"1"},{"tradingsymbol":"LAKSHMI MACHINES LTD","mis_multiplier":"2.00","nrml_multiplier":"1"},{"tradingsymbol":"LAKSHMI VILAS BANK LTD","mis_multiplier":"2.00","nrml_multiplier":"1"},{"tradingsymbol":"Larsen & Toubro Infotech Limit","mis_multiplier":"5.00","nrml_multiplier":"1"},{"tradingsymbol":"LARSEN & TOUBRO LTD.","mis_multiplier":"8.00","nrml_multiplier":"1"},{"tradingsymbol":"Laurus Labs Ltd","mis_multiplier":"1.00","nrml_multiplier":"1"},{"tradingsymbol":"Lemon Tree Hotels Limited","mis_multiplier":"2.00","nrml_multiplier":"1"},{"tradingsymbol":"LIBERTY SHOES LTD","mis_multiplier":"1.00","nrml_multiplier":"1"},{"tradingsymbol":"LIC HOUSING FINANCE LTD","mis_multiplier":"5.00","nrml_multiplier":"1"},{"tradingsymbol":"LINDE INDIA LIMITED","mis_multiplier":"3.00","nrml_multiplier":"1"},{"tradingsymbol":"LOVABLE LINGERIE LTD","mis_multiplier":"3.00","nrml_multiplier":"1"},{"tradingsymbol":"LUMAX AUTO TECHNOLOGIES LTD.","mis_multiplier":"1.00","nrml_multiplier":"1"},{"tradingsymbol":"LUPIN LIMITED","mis_multiplier":"8.00","nrml_multiplier":"1"},{"tradingsymbol":"M&M FIN. SERVICES LTD","mis_multiplier":"5.00","nrml_multiplier":"1"},{"tradingsymbol":"MAGMA FINCORP LIMITED","mis_multiplier":"2.50","nrml_multiplier":"1"},{"tradingsymbol":"Mahanagar Gas Limited","mis_multiplier":"5.00","nrml_multiplier":"1"},{"tradingsymbol":"MAHANAGAR TELEPHONE NIGAM","mis_multiplier":"2.00","nrml_multiplier":"1"},{"tradingsymbol":"MAHARASHTRA SEAMLESS LTD","mis_multiplier":"2.00","nrml_multiplier":"1"},{"tradingsymbol":"MAHINDRA & MAHINDRA LTD","mis_multiplier":"8.00","nrml_multiplier":"1"},{"tradingsymbol":"MAHINDRA CIE AUTO LTD","mis_multiplier":"3.00","nrml_multiplier":"1"},{"tradingsymbol":"MAHINDRA HOLIDAYS LTD","mis_multiplier":"3.00","nrml_multiplier":"1"},{"tradingsymbol":"MAHINDRA LIFESPACE DEVLTD","mis_multiplier":"2.00","nrml_multiplier":"1"},{"tradingsymbol":"Mahindra Logistics Limited","mis_multiplier":"3.00","nrml_multiplier":"1"},{"tradingsymbol":"MAN INDUSTRIES (I) LTD.","mis_multiplier":"1.00","nrml_multiplier":"1"},{"tradingsymbol":"MAN INFRA LTD","mis_multiplier":"2.00","nrml_multiplier":"1"},{"tradingsymbol":"MANAPPURAM FINANCE LTD","mis_multiplier":"5.00","nrml_multiplier":"1"},{"tradingsymbol":"MARICO LIMITED","mis_multiplier":"8.00","nrml_multiplier":"1"},{"tradingsymbol":"MARKSANS PHARMA LIMITED","mis_multiplier":"1.00","nrml_multiplier":"1"},{"tradingsymbol":"MARUTI SUZUKI INDIA LTD.","mis_multiplier":"8.00","nrml_multiplier":"1"},{"tradingsymbol":"MAS Financial Services Limited","mis_multiplier":"5.00","nrml_multiplier":"1"},{"tradingsymbol":"MASTEK LTD","mis_multiplier":"2.00","nrml_multiplier":"1"},{"tradingsymbol":"MAX FINANCIAL SERV LTD","mis_multiplier":"5.00","nrml_multiplier":"1"},{"tradingsymbol":"Max India Ltd.","mis_multiplier":"2.00","nrml_multiplier":"1"},{"tradingsymbol":"MAYUR UNIQUOTERS LTD","mis_multiplier":"1.00","nrml_multiplier":"1"},{"tradingsymbol":"Mazagon Dock Shipbuilders Limited","mis_multiplier":"2.00","nrml_multiplier":"1"},{"tradingsymbol":"MERCATOR LIMITED","mis_multiplier":"3.00","nrml_multiplier":"1"},{"tradingsymbol":"Metropolis Healthcare Limited","mis_multiplier":"5.00","nrml_multiplier":"1"},{"tradingsymbol":"MINDTREE LIMITED","mis_multiplier":"5.00","nrml_multiplier":"1"},{"tradingsymbol":"MIRZA INTERNATIONAL LIMIT","mis_multiplier":"1.00","nrml_multiplier":"1"},{"tradingsymbol":"MMTC LTD","mis_multiplier":"1.00","nrml_multiplier":"1"},{"tradingsymbol":"MOIL LIMITED","mis_multiplier":"3.00","nrml_multiplier":"1"},{"tradingsymbol":"MOTHERSON SUMI SYSTEMS LT","mis_multiplier":"5.00","nrml_multiplier":"1"},{"tradingsymbol":"MOTILAL OSWAL FIN LTD","mis_multiplier":"5.00","nrml_multiplier":"1"},{"tradingsymbol":"MPHASIS LIMITED","mis_multiplier":"4.00","nrml_multiplier":"1"},{"tradingsymbol":"MPS LTD.","mis_multiplier":"2.00","nrml_multiplier":"1"},{"tradingsymbol":"MRF LTD","mis_multiplier":"8.00","nrml_multiplier":"1"},{"tradingsymbol":"MRPL","mis_multiplier":"3.00","nrml_multiplier":"1"},{"tradingsymbol":"MULTI COMMODITY EXCHANGE","mis_multiplier":"3.00","nrml_multiplier":"1"},{"tradingsymbol":"MUNJAL AUTO IND. LTD.","mis_multiplier":"1.00","nrml_multiplier":"1"},{"tradingsymbol":"MUNJAL SHOWA LTD","mis_multiplier":"1.00","nrml_multiplier":"1"},{"tradingsymbol":"MUSIC BROADCAST","mis_multiplier":"2.00","nrml_multiplier":"1"},{"tradingsymbol":"MUTHOOT FINANCE LIMITED","mis_multiplier":"5.00","nrml_multiplier":"1"},{"tradingsymbol":"NARAYANA HRUDAYALAYA LTD.","mis_multiplier":"2.50","nrml_multiplier":"1"},{"tradingsymbol":"NATCO PHARMA LTD.","mis_multiplier":"4.00","nrml_multiplier":"1"},{"tradingsymbol":"NATIONAL ALUMINIUM CO LTD","mis_multiplier":"4.00","nrml_multiplier":"1"},{"tradingsymbol":"NAVA BHARAT VENTURES LTD","mis_multiplier":"2.00","nrml_multiplier":"1"},{"tradingsymbol":"Navin Fluorine International Limited","mis_multiplier":"2.00","nrml_multiplier":"1"},{"tradingsymbol":"NAVNEET EDUCATION LTD","mis_multiplier":"2.00","nrml_multiplier":"1"},{"tradingsymbol":"NBCC (INDIA) LIMITED","mis_multiplier":"2.00","nrml_multiplier":"1"},{"tradingsymbol":"NCC LIMITED","mis_multiplier":"1.00","nrml_multiplier":"1"},{"tradingsymbol":"NESCO LTD.","mis_multiplier":"5.00","nrml_multiplier":"1"},{"tradingsymbol":"NESTLE INDIA LIMITED","mis_multiplier":"8.00","nrml_multiplier":"1"},{"tradingsymbol":"NETWORK18 MEDIA & INV LTD","mis_multiplier":"5.00","nrml_multiplier":"1"},{"tradingsymbol":"Newgen Software Technologies Limited","mis_multiplier":"2.00","nrml_multiplier":"1"},{"tradingsymbol":"NHPC LTD","mis_multiplier":"5.00","nrml_multiplier":"1"},{"tradingsymbol":"NIIT LIMITED","mis_multiplier":"2.00","nrml_multiplier":"1"},{"tradingsymbol":"NIIT TECHNOLOGIES LTD","mis_multiplier":"4.00","nrml_multiplier":"1"},{"tradingsymbol":"NILKAMAL LTD.","mis_multiplier":"1.00","nrml_multiplier":"1"},{"tradingsymbol":"Nippon Life India Asset Management Limited","mis_multiplier":"5.00","nrml_multiplier":"1"},{"tradingsymbol":"NLC India Ltd","mis_multiplier":"1.00","nrml_multiplier":"1"},{"tradingsymbol":"NMDC LTD.","mis_multiplier":"9.00","nrml_multiplier":"1"},{"tradingsymbol":"NOCIL LTD","mis_multiplier":"2.00","nrml_multiplier":"1"},{"tradingsymbol":"NOIDA TOLL BRIDGE CO LTD","mis_multiplier":"1.00","nrml_multiplier":"1"},{"tradingsymbol":"NOVARTIS INDIA LTD.","mis_multiplier":"4.00","nrml_multiplier":"1"},{"tradingsymbol":"NRB BEARINGS LTD","mis_multiplier":"1.00","nrml_multiplier":"1"},{"tradingsymbol":"NTPC LTD","mis_multiplier":"8.00","nrml_multiplier":"1"},{"tradingsymbol":"OBEROI REALTY LIMITED","mis_multiplier":"4.00","nrml_multiplier":"1"},{"tradingsymbol":"OIL AND NATURAL GAS CORP.","mis_multiplier":"5.00","nrml_multiplier":"1"},{"tradingsymbol":"OIL INDIA LTD","mis_multiplier":"5.00","nrml_multiplier":"1"},{"tradingsymbol":"ORACLE FIN SERV SOFT LTD.","mis_multiplier":"8.00","nrml_multiplier":"1"},{"tradingsymbol":"Orient Electric Limited","mis_multiplier":"2.00","nrml_multiplier":"1"},{"tradingsymbol":"ORIENT REFRACTORIES LTD.","mis_multiplier":"4.00","nrml_multiplier":"1"},{"tradingsymbol":"P&G HYGIENE & HEALTH CARE","mis_multiplier":"5.00","nrml_multiplier":"1"},{"tradingsymbol":"PAGE INDUSTRIES LTD","mis_multiplier":"6.67","nrml_multiplier":"1"},{"tradingsymbol":"Parag Milk Foods Ltd","mis_multiplier":"1.00","nrml_multiplier":"1"},{"tradingsymbol":"PC JEWELLER LTD.","mis_multiplier":"2.00","nrml_multiplier":"1"},{"tradingsymbol":"PERSISTENT SYSTEMS LTD","mis_multiplier":"5.00","nrml_multiplier":"1"},{"tradingsymbol":"PETRONET LNG LIMITED","mis_multiplier":"6.67","nrml_multiplier":"1"},{"tradingsymbol":"PFIZER LTD","mis_multiplier":"5.00","nrml_multiplier":"1"},{"tradingsymbol":"PI INDUSTRIES LTD","mis_multiplier":"3.00","nrml_multiplier":"1"},{"tradingsymbol":"PIDILITE INDUSTRIES LTD","mis_multiplier":"8.00","nrml_multiplier":"1"},{"tradingsymbol":"PIRAMAL ENTERPRISES LTD","mis_multiplier":"5.00","nrml_multiplier":"1"},{"tradingsymbol":"PNB Housing Finance Limited","mis_multiplier":"4.00","nrml_multiplier":"1"},{"tradingsymbol":"Polycab India Limited","mis_multiplier":"2.00","nrml_multiplier":"1"},{"tradingsymbol":"POWER FIN CORP LTD.","mis_multiplier":"8.00","nrml_multiplier":"1"},{"tradingsymbol":"POWER GRID CORP. LTD.","mis_multiplier":"8.00","nrml_multiplier":"1"},{"tradingsymbol":"PRAJ INDUSTRIES LTD","mis_multiplier":"1.00","nrml_multiplier":"1"},{"tradingsymbol":"Prataap Snacks Limited","mis_multiplier":"2.00","nrml_multiplier":"1"},{"tradingsymbol":"PRESTIGE ESTATE LTD","mis_multiplier":"2.00","nrml_multiplier":"1"},{"tradingsymbol":"PRISM CEMENTS LTD","mis_multiplier":"2.00","nrml_multiplier":"1"},{"tradingsymbol":"PROCTER & GAMBLE HEALTH LIMITE","mis_multiplier":"4.00","nrml_multiplier":"1"},{"tradingsymbol":"PSP Projects Limited","mis_multiplier":"2.00","nrml_multiplier":"1"},{"tradingsymbol":"PTC INDIA FIN SERV LTD","mis_multiplier":"1.00","nrml_multiplier":"1"},{"tradingsymbol":"PTC INDIA LIMITED","mis_multiplier":"5.00","nrml_multiplier":"1"},{"tradingsymbol":"PUNJAB NATIONAL BANK","mis_multiplier":"5.00","nrml_multiplier":"1"},{"tradingsymbol":"PVR LIMITED","mis_multiplier":"4.00","nrml_multiplier":"1"},{"tradingsymbol":"Quess Corp Limited","mis_multiplier":"5.00","nrml_multiplier":"1"},{"tradingsymbol":"QUICK HEAL TECH LTD","mis_multiplier":"1.00","nrml_multiplier":"1"},{"tradingsymbol":"R SHARES BANK BEES","mis_multiplier":"12.00","nrml_multiplier":"1"},{"tradingsymbol":"R SHARES GOLD BEES","mis_multiplier":"15.00","nrml_multiplier":"1"},{"tradingsymbol":"R SHARES LIQUID BEES","mis_multiplier":"25.00","nrml_multiplier":"1"},{"tradingsymbol":"R SHARES NIFTY BEES","mis_multiplier":"12.00","nrml_multiplier":"1"},{"tradingsymbol":"Rail Vikas Nigam Limited","mis_multiplier":"2.00","nrml_multiplier":"1"},{"tradingsymbol":"RAJESH EXPORTS LTD","mis_multiplier":"1.00","nrml_multiplier":"1"},{"tradingsymbol":"RALLIS INDIA LTD","mis_multiplier":"4.00","nrml_multiplier":"1"},{"tradingsymbol":"RAMCO INDUSTRIES LIMITED","mis_multiplier":"1.00","nrml_multiplier":"1"},{"tradingsymbol":"RAMCO SYSTEMS LTD.","mis_multiplier":"2.00","nrml_multiplier":"1"},{"tradingsymbol":"RANE BRAKE LINING LTD.","mis_multiplier":"2.00","nrml_multiplier":"1"},{"tradingsymbol":"RASHTRIYA CHEMICALS & FER","mis_multiplier":"3.00","nrml_multiplier":"1"},{"tradingsymbol":"RATTANINDIA POWER LIMITED","mis_multiplier":"3.00","nrml_multiplier":"1"},{"tradingsymbol":"RAYMOND LTD","mis_multiplier":"5.00","nrml_multiplier":"1"},{"tradingsymbol":"RBL Bank Limited","mis_multiplier":"4.00","nrml_multiplier":"1"},{"tradingsymbol":"REDINGTON (INDIA) LTD.","mis_multiplier":"1.00","nrml_multiplier":"1"},{"tradingsymbol":"RELAXO FOOT LTD.","mis_multiplier":"4.00","nrml_multiplier":"1"},{"tradingsymbol":"RELIANCE INDUSTRIAL INFRA","mis_multiplier":"1.00","nrml_multiplier":"1"},{"tradingsymbol":"RELIANCE INDUSTRIES LTD","mis_multiplier":"8.00","nrml_multiplier":"1"},{"tradingsymbol":"RELIGARE ENTER. LTD.","mis_multiplier":"3.00","nrml_multiplier":"1"},{"tradingsymbol":"REPCO HOME FINANCE LTD","mis_multiplier":"5.00","nrml_multiplier":"1"},{"tradingsymbol":"RICO AUTO INDUSTRIES LTD","mis_multiplier":"1.00","nrml_multiplier":"1"},{"tradingsymbol":"RITES Limited","mis_multiplier":"2.00","nrml_multiplier":"1"},{"tradingsymbol":"Route Mobile Limited","mis_multiplier":"2.00","nrml_multiplier":"1"},{"tradingsymbol":"RURAL ELEC CORP. LTD.","mis_multiplier":"8.00","nrml_multiplier":"1"},{"tradingsymbol":"S Chand and Company Ltd","mis_multiplier":"2.00","nrml_multiplier":"1"},{"tradingsymbol":"S H Kelkar and Company Ltd","mis_multiplier":"1.00","nrml_multiplier":"1"},{"tradingsymbol":"SADBHAV ENGINEERING LTD","mis_multiplier":"1.00","nrml_multiplier":"1"},{"tradingsymbol":"SANOFI INDIA LIMITED","mis_multiplier":"4.00","nrml_multiplier":"1"},{"tradingsymbol":"SAREGAMA INDIA LTD.","mis_multiplier":"2.00","nrml_multiplier":"1"},{"tradingsymbol":"SATIN CREDITCARE NETWORK LIMIT","mis_multiplier":"4.00","nrml_multiplier":"1"},{"tradingsymbol":"SBI Cards and Payment Services Ltd","mis_multiplier":"1.00","nrml_multiplier":"1"},{"tradingsymbol":"SBI Life Insurance Company Limited","mis_multiplier":"6.67","nrml_multiplier":"1"},{"tradingsymbol":"Schaeffler India Limited","mis_multiplier":"4.00","nrml_multiplier":"1"},{"tradingsymbol":"SCHNEIDER ELECTRIC INFRA","mis_multiplier":"3.00","nrml_multiplier":"1"},{"tradingsymbol":"Security and Intelligence Services (India) Limited","mis_multiplier":"2.00","nrml_multiplier":"1"},{"tradingsymbol":"SELAN EXPLO. TECH LTD","mis_multiplier":"3.00","nrml_multiplier":"1"},{"tradingsymbol":"SEQUENT SCIENTIFIC LTD.","mis_multiplier":"2.00","nrml_multiplier":"1"},{"tradingsymbol":"Shalby Limited","mis_multiplier":"1.00","nrml_multiplier":"1"},{"tradingsymbol":"Sharda Cropchem Ltd","mis_multiplier":"1.00","nrml_multiplier":"1"},{"tradingsymbol":"Sheela Foam Limited","mis_multiplier":"2.50","nrml_multiplier":"1"},{"tradingsymbol":"Shemaroo Entertainment Ltd","mis_multiplier":"2.00","nrml_multiplier":"1"},{"tradingsymbol":"SHILPA MEDICARE LTD.","mis_multiplier":"2.00","nrml_multiplier":"1"},{"tradingsymbol":"SHIPPING CORP OF INDIA LT","mis_multiplier":"3.00","nrml_multiplier":"1"},{"tradingsymbol":"SHOPPERS STOP LIMITED","mis_multiplier":"4.00","nrml_multiplier":"1"},{"tradingsymbol":"SHREE CEMENTS LTD","mis_multiplier":"5.00","nrml_multiplier":"1"},{"tradingsymbol":"SHREE RENUKA SUGARS LTD","mis_multiplier":"3.00","nrml_multiplier":"1"},{"tradingsymbol":"SHRIRAM CITYUNI FIN.LTD.","mis_multiplier":"5.00","nrml_multiplier":"1"},{"tradingsymbol":"SHRIRAM TRANSPORT FIN CO.","mis_multiplier":"5.00","nrml_multiplier":"1"},{"tradingsymbol":"SIEMENS LTD","mis_multiplier":"8.00","nrml_multiplier":"1"},{"tradingsymbol":"SINTEX INDUSTRIES LTD","mis_multiplier":"2.00","nrml_multiplier":"1"},{"tradingsymbol":"SJVN LTD","mis_multiplier":"1.00","nrml_multiplier":"1"},{"tradingsymbol":"SKF INDIA LTD","mis_multiplier":"4.00","nrml_multiplier":"1"},{"tradingsymbol":"SML ISUZU LIMITED","mis_multiplier":"1.00","nrml_multiplier":"1"},{"tradingsymbol":"SNOWMAN LOGISTICS LTD.","mis_multiplier":"1.00","nrml_multiplier":"1"},{"tradingsymbol":"SOBHA LIMITED","mis_multiplier":"3.00","nrml_multiplier":"1"},{"tradingsymbol":"SOLAR INDUSTRIES INDIA LTD.","mis_multiplier":"4.00","nrml_multiplier":"1"},{"tradingsymbol":"SONATA SOFTWARE LTD","mis_multiplier":"1.00","nrml_multiplier":"1"},{"tradingsymbol":"Spandana Sphoorty Financial Limited","mis_multiplier":"5.00","nrml_multiplier":"1"},{"tradingsymbol":"Spencer's Retail Limited","mis_multiplier":"2.00","nrml_multiplier":"1"},{"tradingsymbol":"SPICEJET LTD.","mis_multiplier":"2.00","nrml_multiplier":"1"},{"tradingsymbol":"SREI INFRASTRUCTURE FINAN","mis_multiplier":"2.00","nrml_multiplier":"1"},{"tradingsymbol":"SRF LTD","mis_multiplier":"5.00","nrml_multiplier":"1"},{"tradingsymbol":"STANDARD CHARTERED PLC","mis_multiplier":"2.00","nrml_multiplier":"1"},{"tradingsymbol":"STATE BANK OF INDIA","mis_multiplier":"8.00","nrml_multiplier":"1"},{"tradingsymbol":"STEEL AUTHORITY OF INDIA","mis_multiplier":"5.00","nrml_multiplier":"1"},{"tradingsymbol":"STERLITE TECHNOLOGIES LTD","mis_multiplier":"2.00","nrml_multiplier":"1"},{"tradingsymbol":"STRIDES SHASUN LIMITED","mis_multiplier":"5.00","nrml_multiplier":"1"},{"tradingsymbol":"SUN PHARMA ADV.RES.CO.LTD","mis_multiplier":"3.00","nrml_multiplier":"1"},{"tradingsymbol":"SUN PHARMACEUTICALS IND.","mis_multiplier":"8.00","nrml_multiplier":"1"},{"tradingsymbol":"SUN TV NETWORK LIMITED","mis_multiplier":"5.00","nrml_multiplier":"1"},{"tradingsymbol":"SUNDARAM FINANCE LTD.","mis_multiplier":"5.00","nrml_multiplier":"1"},{"tradingsymbol":"SUNDRAM FASTENERS LTD","mis_multiplier":"2.00","nrml_multiplier":"1"},{"tradingsymbol":"SUNTECK REALTY LTD.","mis_multiplier":"2.00","nrml_multiplier":"1"},{"tradingsymbol":"SUPRAJIT ENGINEERING LTD.","mis_multiplier":"2.00","nrml_multiplier":"1"},{"tradingsymbol":"SUPREME INDUSTRIES LTD","mis_multiplier":"2.50","nrml_multiplier":"1"},{"tradingsymbol":"SUVEN LIFE SCIENCES LTD.","mis_multiplier":"2.50","nrml_multiplier":"1"},{"tradingsymbol":"SUZLON ENERGY LIMITED","mis_multiplier":"4.00","nrml_multiplier":"1"},{"tradingsymbol":"SWARAJ ENGINES LTD.","mis_multiplier":"2.50","nrml_multiplier":"1"},{"tradingsymbol":"SYMPHONY LIMITED","mis_multiplier":"5.00","nrml_multiplier":"1"},{"tradingsymbol":"SYNGENE INTERNATIONAL LTD","mis_multiplier":"5.00","nrml_multiplier":"1"},{"tradingsymbol":"TAKE SOLUTIONS LTD","mis_multiplier":"1.00","nrml_multiplier":"1"},{"tradingsymbol":"TAMILNADU NEWSPRT & PAPER","mis_multiplier":"2.50","nrml_multiplier":"1"},{"tradingsymbol":"TATA CHEMICALS LTD","mis_multiplier":"6.67","nrml_multiplier":"1"},{"tradingsymbol":"TATA COFFEE LIMITED","mis_multiplier":"4.00","nrml_multiplier":"1"},{"tradingsymbol":"TATA COMMUNICATIONS LTD","mis_multiplier":"8.00","nrml_multiplier":"1"},{"tradingsymbol":"TATA CONSULTANCY SERV LT","mis_multiplier":"10.00","nrml_multiplier":"1"},{"tradingsymbol":"TATA ELXSI LIMITED","mis_multiplier":"5.00","nrml_multiplier":"1"},{"tradingsymbol":"TATA GLOBAL BEVERAGES LTD","mis_multiplier":"6.67","nrml_multiplier":"1"},{"tradingsymbol":"TATA INVESTMENT CORP LTD","mis_multiplier":"2.50","nrml_multiplier":"1"},{"tradingsymbol":"TATA METALIKS LTD.","mis_multiplier":"2.00","nrml_multiplier":"1"},{"tradingsymbol":"TATA MOTORS DVR 'A' ORD","mis_multiplier":"5.00","nrml_multiplier":"1"},{"tradingsymbol":"TATA MOTORS LIMITED","mis_multiplier":"8.00","nrml_multiplier":"1"},{"tradingsymbol":"TATA POWER CO LTD","mis_multiplier":"6.67","nrml_multiplier":"1"},{"tradingsymbol":"TATA SPONGE IRON LIMITED","mis_multiplier":"2.50","nrml_multiplier":"1"},{"tradingsymbol":"TATA STEEL LIMITED","mis_multiplier":"8.00","nrml_multiplier":"1"},{"tradingsymbol":"TCI Express Limited","mis_multiplier":"2.00","nrml_multiplier":"1"},{"tradingsymbol":"TCNS Clothing Co. Limited","mis_multiplier":"2.00","nrml_multiplier":"1"},{"tradingsymbol":"TEAMLEASE SERVICES LTD.","mis_multiplier":"2.50","nrml_multiplier":"1"},{"tradingsymbol":"TECH MAHINDRA LIMITED","mis_multiplier":"8.00","nrml_multiplier":"1"},{"tradingsymbol":"TEXMACO RAIL & ENG. LTD.","mis_multiplier":"2.00","nrml_multiplier":"1"},{"tradingsymbol":"The Anup Engineering Ltd","mis_multiplier":"2.00","nrml_multiplier":"1"},{"tradingsymbol":"THE GE SHPG.LTD","mis_multiplier":"3.00","nrml_multiplier":"1"},{"tradingsymbol":"THE INDIA CEMENTS LIMITED","mis_multiplier":"5.00","nrml_multiplier":"1"},{"tradingsymbol":"THE INDIAN HOTELS CO. LTD","mis_multiplier":"3.00","nrml_multiplier":"1"},{"tradingsymbol":"The New India Assurance Company Limited","mis_multiplier":"2.00","nrml_multiplier":"1"},{"tradingsymbol":"THE PHOENIX MILLS LTD","mis_multiplier":"3.00","nrml_multiplier":"1"},{"tradingsymbol":"THE RAMCO CEMENTS LIMITED","mis_multiplier":"4.00","nrml_multiplier":"1"},{"tradingsymbol":"THE SOUTH INDIAN BANK LTD","mis_multiplier":"3.00","nrml_multiplier":"1"},{"tradingsymbol":"THE STATE TRADING CORPN","mis_multiplier":"3.00","nrml_multiplier":"1"},{"tradingsymbol":"THERMAX LTD","mis_multiplier":"3.00","nrml_multiplier":"1"},{"tradingsymbol":"THOMAS COOK (INDIA) LTD","mis_multiplier":"2.00","nrml_multiplier":"1"},{"tradingsymbol":"Thyrocare Technologies Limited","mis_multiplier":"5.00","nrml_multiplier":"1"},{"tradingsymbol":"TILAKNAGAR INDUSTRIES LTD","mis_multiplier":"1.00","nrml_multiplier":"1"},{"tradingsymbol":"TITAGARH WAGONS LTD.","mis_multiplier":"1.00","nrml_multiplier":"1"},{"tradingsymbol":"TITAN COMPANY LIMITED","mis_multiplier":"8.00","nrml_multiplier":"1"},{"tradingsymbol":"TORRENT PHARMACEUTICALS L","mis_multiplier":"5.00","nrml_multiplier":"1"},{"tradingsymbol":"TORRENT POWER LTD","mis_multiplier":"5.00","nrml_multiplier":"1"},{"tradingsymbol":"TOURISM FINANCE CORPORATION OF","mis_multiplier":"2.00","nrml_multiplier":"1"},{"tradingsymbol":"TRANSPORT CORPORATION OF INDIA","mis_multiplier":"2.00","nrml_multiplier":"1"},{"tradingsymbol":"TRENT LTD","mis_multiplier":"3.00","nrml_multiplier":"1"},{"tradingsymbol":"TRF LIMITED","mis_multiplier":"1.00","nrml_multiplier":"1"},{"tradingsymbol":"TRIDENT LIMITED","mis_multiplier":"2.00","nrml_multiplier":"1"},{"tradingsymbol":"TRIVENI TURBINE LTD.","mis_multiplier":"2.50","nrml_multiplier":"1"},{"tradingsymbol":"TTK PRESTIGE LTD","mis_multiplier":"2.50","nrml_multiplier":"1"},{"tradingsymbol":"TV TODAY NETWORK LTD","mis_multiplier":"2.00","nrml_multiplier":"1"},{"tradingsymbol":"TV18 BROADCAST LIMITED","mis_multiplier":"3.00","nrml_multiplier":"1"},{"tradingsymbol":"TVS MOTOR COMPANY  LTD","mis_multiplier":"6.67","nrml_multiplier":"1"},{"tradingsymbol":"TVS SRICHAKRA LTD.","mis_multiplier":"1.00","nrml_multiplier":"1"},{"tradingsymbol":"UCO BANK","mis_multiplier":"5.00","nrml_multiplier":"1"},{"tradingsymbol":"UFLEX LTD.","mis_multiplier":"1.00","nrml_multiplier":"1"},{"tradingsymbol":"Ujjivan Financial Services Lim","mis_multiplier":"4.00","nrml_multiplier":"1"},{"tradingsymbol":"Ujjivan Small Finance Bank Limited","mis_multiplier":"2.00","nrml_multiplier":"1"},{"tradingsymbol":"ULTRATECH CEMENT LIMITED","mis_multiplier":"8.00","nrml_multiplier":"1"},{"tradingsymbol":"UNICHEM LABORATORIES LTD","mis_multiplier":"2.00","nrml_multiplier":"1"},{"tradingsymbol":"UNION BANK OF INDIA","mis_multiplier":"5.00","nrml_multiplier":"1"},{"tradingsymbol":"UNITED BREWERIES LTD","mis_multiplier":"8.00","nrml_multiplier":"1"},{"tradingsymbol":"UNITED SPIRITS LIMITED","mis_multiplier":"4.00","nrml_multiplier":"1"},{"tradingsymbol":"UNITED SPIRITS LTD.","mis_multiplier":"8.00","nrml_multiplier":"1"},{"tradingsymbol":"UPL LIMITED","mis_multiplier":"5.00","nrml_multiplier":"1"},{"tradingsymbol":"USHA MARTIN LTD.","mis_multiplier":"1.00","nrml_multiplier":"1"},{"tradingsymbol":"UTI Asset Management Company Limited","mis_multiplier":"2.00","nrml_multiplier":"1"},{"tradingsymbol":"V-GUARD IND LTD.","mis_multiplier":"2.50","nrml_multiplier":"1"},{"tradingsymbol":"V-MART RETAIL LTD.","mis_multiplier":"2.00","nrml_multiplier":"1"},{"tradingsymbol":"VA TECH WABAG LTD","mis_multiplier":"2.00","nrml_multiplier":"1"},{"tradingsymbol":"VADILAL INDUSTRIES LTD","mis_multiplier":"1.00","nrml_multiplier":"1"},{"tradingsymbol":"VAKRANGEE LIMITED","mis_multiplier":"1.00","nrml_multiplier":"1"},{"tradingsymbol":"VARDHMAN TEXTILES LIMITED","mis_multiplier":"1.00","nrml_multiplier":"1"},{"tradingsymbol":"Varroc Engineering Limited","mis_multiplier":"2.00","nrml_multiplier":"1"},{"tradingsymbol":"Varun Beverages Limited","mis_multiplier":"5.00","nrml_multiplier":"1"},{"tradingsymbol":"VEDANTA LIMITED","mis_multiplier":"8.00","nrml_multiplier":"1"},{"tradingsymbol":"VINATI ORGANICS LTD.","mis_multiplier":"4.00","nrml_multiplier":"1"},{"tradingsymbol":"VIP INDUSTRIES LTD","mis_multiplier":"3.00","nrml_multiplier":"1"},{"tradingsymbol":"VOLTAS LTD","mis_multiplier":"6.67","nrml_multiplier":"1"},{"tradingsymbol":"VRL LOGISTICS LIMITED","mis_multiplier":"1.00","nrml_multiplier":"1"},{"tradingsymbol":"VST INDUSTRIES LTD","mis_multiplier":"5.00","nrml_multiplier":"1"},{"tradingsymbol":"WABCO INDIA LIMITED","mis_multiplier":"3.00","nrml_multiplier":"1"},{"tradingsymbol":"WALCHANDNAGAR INDUSTRIES","mis_multiplier":"1.00","nrml_multiplier":"1"},{"tradingsymbol":"WELSPUN CORP LIMITED","mis_multiplier":"3.00","nrml_multiplier":"1"},{"tradingsymbol":"WELSPUN INDIA LTD","mis_multiplier":"3.00","nrml_multiplier":"1"},{"tradingsymbol":"WESTLIFE DEVELOPMENT LTD.","mis_multiplier":"2.00","nrml_multiplier":"1"},{"tradingsymbol":"WHIRLPOOL OF INDIA LTD","mis_multiplier":"2.50","nrml_multiplier":"1"},{"tradingsymbol":"WIPRO LTD","mis_multiplier":"8.00","nrml_multiplier":"1"},{"tradingsymbol":"WOCKHARDT LIMITED","mis_multiplier":"2.50","nrml_multiplier":"1"},{"tradingsymbol":"WONDERLA HOLIDAYS LTD.","mis_multiplier":"2.00","nrml_multiplier":"1"},{"tradingsymbol":"ZEE ENTERTAINMENT ENT LTD","mis_multiplier":"4.00","nrml_multiplier":"1"},{"tradingsymbol":"ZEE LEARN LTD.","mis_multiplier":"2.00","nrml_multiplier":"1"},{"tradingsymbol":"ZEE MEDIA CORPORATION LTD","mis_multiplier":"1.00","nrml_multiplier":"1"},{"tradingsymbol":"ZENSAR TECHNOLOGIES  LTD","mis_multiplier":"2.00","nrml_multiplier":"1"},{"tradingsymbol":"ZYDUS WELLNESS LIMITED","mis_multiplier":"3.00","nrml_multiplier":"1"}]