[{"scrip":"AARTIIND","expiry":"Mar-2021","lot":"425","price":"1276.25","nrml":"133582","mis":"66791","co_margin":"69970.41","bo_margin":"69970.41"},{"scrip":"AARTIIND","expiry":"Apr-2021","lot":"425","price":"1279.15","nrml":"133850","mis":"66925","co_margin":"70129.4","bo_margin":"70129.4"},{"scrip":"AARTIIND","expiry":"May-2021","lot":"425","price":"1286.55","nrml":"133813","mis":"66906.5","co_margin":"70535.1","bo_margin":"70535.1"},{"scrip":"ACC","expiry":"Mar-2021","lot":"500","price":"1835.05","nrml":"187707","mis":"93853.5","co_margin":"96982.39","bo_margin":"96982.39"},{"scrip":"ACC","expiry":"Apr-2021","lot":"500","price":"1839.20","nrml":"188167","mis":"94083.5","co_margin":"97201.72","bo_margin":"97201.72"},{"scrip":"ACC","expiry":"May-2021","lot":"500","price":"1849.85","nrml":"188670","mis":"94335","co_margin":"97764.57","bo_margin":"97764.57"},{"scrip":"ADANIENT","expiry":"Mar-2021","lot":"2000","price":"898.10","nrml":"561954","mis":"280977","co_margin":"290625.16","bo_margin":"290625.16"},{"scrip":"ADANIENT","expiry":"Apr-2021","lot":"2000","price":"900.15","nrml":"564191","mis":"282095.5","co_margin":"291288.54","bo_margin":"291288.54"},{"scrip":"ADANIENT","expiry":"May-2021","lot":"2000","price":"905.35","nrml":"566404","mis":"283202","co_margin":"292971.26","bo_margin":"292971.26"},{"scrip":"ADANIPORTS","expiry":"Mar-2021","lot":"2500","price":"745.35","nrml":"657965","mis":"328982.5","co_margin":"339134.25","bo_margin":"339134.25"},{"scrip":"ADANIPORTS","expiry":"Apr-2021","lot":"2500","price":"747.05","nrml":"660405","mis":"330202.5","co_margin":"339907.75","bo_margin":"339907.75"},{"scrip":"ADANIPORTS","expiry":"May-2021","lot":"2500","price":"759.10","nrml":"662721","mis":"331360.5","co_margin":"345390.5","bo_margin":"345390.5"},{"scrip":"ALKEM","expiry":"Mar-2021","lot":"200","price":"2739.80","nrml":"107636","mis":"53818","co_margin":"56056.31","bo_margin":"56056.31"},{"scrip":"ALKEM","expiry":"Apr-2021","lot":"200","price":"2745.95","nrml":"108002","mis":"54001","co_margin":"56182.14","bo_margin":"56182.14"},{"scrip":"ALKEM","expiry":"May-2021","lot":"200","price":"2761.90","nrml":"108558","mis":"54279","co_margin":"56508.47","bo_margin":"56508.47"},{"scrip":"AMARAJABAT","expiry":"Mar-2021","lot":"1000","price":"896.10","nrml":"203042","mis":"101521","co_margin":"107800.83","bo_margin":"107800.83"},{"scrip":"AMARAJABAT","expiry":"Apr-2021","lot":"1000","price":"898.15","nrml":"203755","mis":"101877.5","co_margin":"108047.45","bo_margin":"108047.45"},{"scrip":"AMARAJABAT","expiry":"May-2021","lot":"1000","price":"903.35","nrml":"203965","mis":"101982.5","co_margin":"108673.01","bo_margin":"108673.01"},{"scrip":"AMBUJACEM","expiry":"Mar-2021","lot":"3000","price":"292.00","nrml":"222414","mis":"111207","co_margin":"117033.6","bo_margin":"117033.6"},{"scrip":"AMBUJACEM","expiry":"Apr-2021","lot":"3000","price":"292.65","nrml":"223309","mis":"111654.5","co_margin":"117294.12","bo_margin":"117294.12"},{"scrip":"AMBUJACEM","expiry":"May-2021","lot":"3000","price":"294.40","nrml":"223627","mis":"111813.5","co_margin":"117995.52","bo_margin":"117995.52"},{"scrip":"APLLTD","expiry":"Mar-2021","lot":"550","price":"934.45","nrml":"133815","mis":"66907.5","co_margin":"69125.94","bo_margin":"69125.94"},{"scrip":"APLLTD","expiry":"Apr-2021","lot":"550","price":"936.55","nrml":"134199","mis":"67099.5","co_margin":"69281.29","bo_margin":"69281.29"},{"scrip":"APLLTD","expiry":"May-2021","lot":"550","price":"942.00","nrml":"134702","mis":"67351","co_margin":"69684.45","bo_margin":"69684.45"},{"scrip":"APOLLOHOSP","expiry":"Mar-2021","lot":"500","price":"2904.25","nrml":"384247","mis":"192123.5","co_margin":"207363.45","bo_margin":"207363.45"},{"scrip":"APOLLOHOSP","expiry":"Apr-2021","lot":"500","price":"2910.75","nrml":"385681","mis":"192840.5","co_margin":"207827.55","bo_margin":"207827.55"},{"scrip":"APOLLOHOSP","expiry":"May-2021","lot":"500","price":"2927.70","nrml":"386077","mis":"193038.5","co_margin":"209037.78","bo_margin":"209037.78"},{"scrip":"APOLLOTYRE","expiry":"Mar-2021","lot":"5000","price":"237.50","nrml":"339667","mis":"169833.5","co_margin":"186912.5","bo_margin":"186912.5"},{"scrip":"APOLLOTYRE","expiry":"Apr-2021","lot":"5000","price":"238.05","nrml":"340925","mis":"170462.5","co_margin":"187345.35","bo_margin":"187345.35"},{"scrip":"APOLLOTYRE","expiry":"May-2021","lot":"5000","price":"239.45","nrml":"341538","mis":"170769","co_margin":"188447.15","bo_margin":"188447.15"},{"scrip":"ASHOKLEY","expiry":"Mar-2021","lot":"9000","price":"123.90","nrml":"368563","mis":"184281.5","co_margin":"196926.66","bo_margin":"196926.66"},{"scrip":"ASHOKLEY","expiry":"Apr-2021","lot":"9000","price":"124.20","nrml":"369922","mis":"184961","co_margin":"197403.48","bo_margin":"197403.48"},{"scrip":"ASHOKLEY","expiry":"May-2021","lot":"9000","price":"124.90","nrml":"371054","mis":"185527","co_margin":"198516.06","bo_margin":"198516.06"},{"scrip":"ASIANPAINT","expiry":"Mar-2021","lot":"300","price":"2431.95","nrml":"148100","mis":"74050","co_margin":"76679.38","bo_margin":"76679.38"},{"scrip":"ASIANPAINT","expiry":"Apr-2021","lot":"300","price":"2437.40","nrml":"148704","mis":"74352","co_margin":"76851.22","bo_margin":"76851.22"},{"scrip":"ASIANPAINT","expiry":"May-2021","lot":"300","price":"2465.00","nrml":"149164","mis":"74582","co_margin":"77721.45","bo_margin":"77721.45"},{"scrip":"AUBANK","expiry":"Mar-2021","lot":"500","price":"1253.30","nrml":"177295","mis":"88647.5","co_margin":"94498.82","bo_margin":"94498.82"},{"scrip":"AUBANK","expiry":"Apr-2021","lot":"500","price":"1256.15","nrml":"178008","mis":"89004","co_margin":"94713.71","bo_margin":"94713.71"},{"scrip":"AUBANK","expiry":"May-2021","lot":"500","price":"1263.45","nrml":"178505","mis":"89252.5","co_margin":"95264.13","bo_margin":"95264.13"},{"scrip":"AUROPHARMA","expiry":"Mar-2021","lot":"650","price":"857.30","nrml":"185255","mis":"92627.5","co_margin":"96013.31","bo_margin":"96013.31"},{"scrip":"AUROPHARMA","expiry":"Apr-2021","lot":"650","price":"859.25","nrml":"185975","mis":"92987.5","co_margin":"96231.7","bo_margin":"96231.7"},{"scrip":"AUROPHARMA","expiry":"May-2021","lot":"650","price":"864.25","nrml":"186550","mis":"93275","co_margin":"96791.68","bo_margin":"96791.68"},{"scrip":"AXISBANK","expiry":"Mar-2021","lot":"1200","price":"760.75","nrml":"282360","mis":"141180","co_margin":"152910.75","bo_margin":"152910.75"},{"scrip":"AXISBANK","expiry":"Apr-2021","lot":"1200","price":"762.45","nrml":"283437","mis":"141718.5","co_margin":"153252.45","bo_margin":"153252.45"},{"scrip":"AXISBANK","expiry":"May-2021","lot":"1200","price":"770.05","nrml":"284312","mis":"142156","co_margin":"154780.05","bo_margin":"154780.05"},{"scrip":"BAJAJ-AUTO","expiry":"Mar-2021","lot":"250","price":"3867.55","nrml":"201571","mis":"100785.5","co_margin":"105777.49","bo_margin":"105777.49"},{"scrip":"BAJAJ-AUTO","expiry":"Apr-2021","lot":"250","price":"3876.25","nrml":"202376","mis":"101188","co_margin":"106015.44","bo_margin":"106015.44"},{"scrip":"BAJAJ-AUTO","expiry":"May-2021","lot":"250","price":"3906.00","nrml":"202880","mis":"101440","co_margin":"106829.1","bo_margin":"106829.1"},{"scrip":"BAJAJFINSV","expiry":"Mar-2021","lot":"125","price":"9991.50","nrml":"363052","mis":"181526","co_margin":"191836.8","bo_margin":"191836.8"},{"scrip":"BAJAJFINSV","expiry":"Apr-2021","lot":"125","price":"10013.90","nrml":"364443","mis":"182221.5","co_margin":"192266.88","bo_margin":"192266.88"},{"scrip":"BAJAJFINSV","expiry":"May-2021","lot":"125","price":"10072.15","nrml":"366728","mis":"183364","co_margin":"193385.28","bo_margin":"193385.28"},{"scrip":"BAJFINANCE","expiry":"Mar-2021","lot":"250","price":"5544.90","nrml":"414861","mis":"207430.5","co_margin":"222766.36","bo_margin":"222766.36"},{"scrip":"BAJFINANCE","expiry":"Apr-2021","lot":"250","price":"5557.35","nrml":"416425","mis":"208212.5","co_margin":"223266.54","bo_margin":"223266.54"},{"scrip":"BAJFINANCE","expiry":"May-2021","lot":"250","price":"5590.30","nrml":"417548","mis":"208774","co_margin":"224590.3","bo_margin":"224590.3"},{"scrip":"BALKRISIND","expiry":"Mar-2021","lot":"400","price":"1625.60","nrml":"164582","mis":"82291","co_margin":"88367.62","bo_margin":"88367.62"},{"scrip":"BALKRISIND","expiry":"Apr-2021","lot":"400","price":"1629.25","nrml":"165230","mis":"82615","co_margin":"88566.03","bo_margin":"88566.03"},{"scrip":"BALKRISIND","expiry":"May-2021","lot":"400","price":"1638.75","nrml":"165516","mis":"82758","co_margin":"89082.45","bo_margin":"89082.45"},{"scrip":"BANDHANBNK","expiry":"Mar-2021","lot":"1800","price":"349.70","nrml":"284536","mis":"142268","co_margin":"148237.83","bo_margin":"148237.83"},{"scrip":"BANDHANBNK","expiry":"Apr-2021","lot":"1800","price":"350.50","nrml":"285561","mis":"142780.5","co_margin":"148576.95","bo_margin":"148576.95"},{"scrip":"BANDHANBNK","expiry":"May-2021","lot":"1800","price":"352.55","nrml":"286402","mis":"143201","co_margin":"149445.95","bo_margin":"149445.95"},{"scrip":"BANKBARODA","expiry":"Mar-2021","lot":"11700","price":"80.00","nrml":"402246","mis":"201123","co_margin":"214999.2","bo_margin":"214999.2"},{"scrip":"BANKBARODA","expiry":"Apr-2021","lot":"11700","price":"80.20","nrml":"404132","mis":"202066","co_margin":"215536.7","bo_margin":"215536.7"},{"scrip":"BANKBARODA","expiry":"May-2021","lot":"11700","price":"80.65","nrml":"406092","mis":"203046","co_margin":"216746.07","bo_margin":"216746.07"},{"scrip":"BANKNIFTY","expiry":"Mar-2021","lot":"25","price":"36007.75","nrml":"184205","mis":"92102.5","co_margin":"96230.71","bo_margin":"96230.71"},{"scrip":"BANKNIFTY","expiry":"Apr-2021","lot":"25","price":"36132.65","nrml":"184857","mis":"92428.5","co_margin":"96564.51","bo_margin":"96564.51"},{"scrip":"BANKNIFTY","expiry":"May-2021","lot":"25","price":"36221.45","nrml":"185396","mis":"92698","co_margin":"96801.83","bo_margin":"96801.83"},{"scrip":"BATAINDIA","expiry":"Mar-2021","lot":"550","price":"1506.05","nrml":"181383","mis":"90691.5","co_margin":"93849.51","bo_margin":"93849.51"},{"scrip":"BATAINDIA","expiry":"Apr-2021","lot":"550","price":"1509.45","nrml":"182096","mis":"91048","co_margin":"94061.38","bo_margin":"94061.38"},{"scrip":"BATAINDIA","expiry":"May-2021","lot":"550","price":"1518.20","nrml":"182795","mis":"91397.5","co_margin":"94606.63","bo_margin":"94606.63"},{"scrip":"BEL","expiry":"Mar-2021","lot":"7600","price":"139.75","nrml":"295461","mis":"147730.5","co_margin":"156234.91","bo_margin":"156234.91"},{"scrip":"BEL","expiry":"Apr-2021","lot":"7600","price":"140.10","nrml":"296626","mis":"148313","co_margin":"156626.2","bo_margin":"156626.2"},{"scrip":"BEL","expiry":"May-2021","lot":"7600","price":"140.90","nrml":"298064","mis":"149032","co_margin":"157520.56","bo_margin":"157520.56"},{"scrip":"BERGEPAINT","expiry":"Mar-2021","lot":"1100","price":"730.35","nrml":"164501","mis":"82250.5","co_margin":"87167.27","bo_margin":"87167.27"},{"scrip":"BERGEPAINT","expiry":"Apr-2021","lot":"1100","price":"732.00","nrml":"165258","mis":"82629","co_margin":"87364.2","bo_margin":"87364.2"},{"scrip":"BERGEPAINT","expiry":"May-2021","lot":"1100","price":"736.25","nrml":"165435","mis":"82717.5","co_margin":"87871.44","bo_margin":"87871.44"},{"scrip":"BHARATFORG","expiry":"Mar-2021","lot":"1500","price":"622.60","nrml":"269331","mis":"134665.5","co_margin":"145221.45","bo_margin":"145221.45"},{"scrip":"BHARATFORG","expiry":"Apr-2021","lot":"1500","price":"624.00","nrml":"270412","mis":"135206","co_margin":"145548","bo_margin":"145548"},{"scrip":"BHARATFORG","expiry":"May-2021","lot":"1500","price":"627.65","nrml":"270630","mis":"135315","co_margin":"146399.36","bo_margin":"146399.36"},{"scrip":"BHARTIARTL","expiry":"Mar-2021","lot":"1851","price":"525.85","nrml":"240954","mis":"120477","co_margin":"129358","bo_margin":"129358"},{"scrip":"BHARTIARTL","expiry":"Apr-2021","lot":"1851","price":"527.05","nrml":"241888","mis":"120944","co_margin":"129653.19","bo_margin":"129653.19"},{"scrip":"BHARTIARTL","expiry":"May-2021","lot":"1851","price":"535.00","nrml":"242703","mis":"121351.5","co_margin":"131608.88","bo_margin":"131608.88"},{"scrip":"BHEL","expiry":"Mar-2021","lot":"21000","price":"54.80","nrml":"501753","mis":"250876.5","co_margin":"266985.6","bo_margin":"266985.6"},{"scrip":"BHEL","expiry":"Apr-2021","lot":"21000","price":"54.95","nrml":"503590","mis":"251795","co_margin":"267716.4","bo_margin":"267716.4"},{"scrip":"BHEL","expiry":"May-2021","lot":"21000","price":"55.75","nrml":"505732","mis":"252866","co_margin":"271614","bo_margin":"271614"},{"scrip":"BIOCON","expiry":"Mar-2021","lot":"2300","price":"402.55","nrml":"262398","mis":"131199","co_margin":"139527.86","bo_margin":"139527.86"},{"scrip":"BIOCON","expiry":"Apr-2021","lot":"2300","price":"403.45","nrml":"263274","mis":"131637","co_margin":"139839.8","bo_margin":"139839.8"},{"scrip":"BIOCON","expiry":"May-2021","lot":"2300","price":"405.80","nrml":"264171","mis":"132085.5","co_margin":"140654.34","bo_margin":"140654.34"},{"scrip":"BOSCHLTD","expiry":"Mar-2021","lot":"50","price":"14997.10","nrml":"182908","mis":"91454","co_margin":"95681.5","bo_margin":"95681.5"},{"scrip":"BOSCHLTD","expiry":"Apr-2021","lot":"50","price":"15030.70","nrml":"183674","mis":"91837","co_margin":"95895.87","bo_margin":"95895.87"},{"scrip":"BOSCHLTD","expiry":"May-2021","lot":"50","price":"15118.10","nrml":"184166","mis":"92083","co_margin":"96453.48","bo_margin":"96453.48"},{"scrip":"BPCL","expiry":"Mar-2021","lot":"1800","price":"445.50","nrml":"353873","mis":"176936.5","co_margin":"189088.02","bo_margin":"189088.02"},{"scrip":"BPCL","expiry":"Apr-2021","lot":"1800","price":"446.50","nrml":"355106","mis":"177553","co_margin":"189512.46","bo_margin":"189512.46"},{"scrip":"BPCL","expiry":"May-2021","lot":"1800","price":"447.40","nrml":"356154","mis":"178077","co_margin":"189894.46","bo_margin":"189894.46"},{"scrip":"BRITANNIA","expiry":"Mar-2021","lot":"200","price":"3480.35","nrml":"144505","mis":"72252.5","co_margin":"75802.02","bo_margin":"75802.02"},{"scrip":"BRITANNIA","expiry":"Apr-2021","lot":"200","price":"3488.15","nrml":"145068","mis":"72534","co_margin":"75971.91","bo_margin":"75971.91"},{"scrip":"BRITANNIA","expiry":"May-2021","lot":"200","price":"3508.45","nrml":"145362","mis":"72681","co_margin":"76414.04","bo_margin":"76414.04"},{"scrip":"CADILAHC","expiry":"Mar-2021","lot":"2200","price":"448.40","nrml":"212265","mis":"106132.5","co_margin":"111176.3","bo_margin":"111176.3"},{"scrip":"CADILAHC","expiry":"Apr-2021","lot":"2200","price":"449.40","nrml":"213119","mis":"106559.5","co_margin":"111424.24","bo_margin":"111424.24"},{"scrip":"CADILAHC","expiry":"May-2021","lot":"2200","price":"452.05","nrml":"213818","mis":"106909","co_margin":"112081.28","bo_margin":"112081.28"},{"scrip":"CANBK","expiry":"Mar-2021","lot":"5400","price":"161.20","nrml":"306936","mis":"153468","co_margin":"165565.3","bo_margin":"165565.3"},{"scrip":"CANBK","expiry":"Apr-2021","lot":"5400","price":"161.60","nrml":"308272","mis":"154136","co_margin":"165976.13","bo_margin":"165976.13"},{"scrip":"CANBK","expiry":"May-2021","lot":"5400","price":"162.50","nrml":"308804","mis":"154402","co_margin":"166900.5","bo_margin":"166900.5"},{"scrip":"CHOLAFIN","expiry":"Mar-2021","lot":"2500","price":"539.40","nrml":"490810","mis":"245405","co_margin":"251630.1","bo_margin":"251630.1"},{"scrip":"CHOLAFIN","expiry":"Apr-2021","lot":"2500","price":"540.65","nrml":"492419","mis":"246209.5","co_margin":"252213.23","bo_margin":"252213.23"},{"scrip":"CHOLAFIN","expiry":"May-2021","lot":"2500","price":"543.75","nrml":"493038","mis":"246519","co_margin":"253659.38","bo_margin":"253659.38"},{"scrip":"CIPLA","expiry":"Mar-2021","lot":"1300","price":"812.40","nrml":"233659","mis":"116829.5","co_margin":"121559.41","bo_margin":"121559.41"},{"scrip":"CIPLA","expiry":"Apr-2021","lot":"1300","price":"814.25","nrml":"234672","mis":"117336","co_margin":"121836.23","bo_margin":"121836.23"},{"scrip":"CIPLA","expiry":"May-2021","lot":"1300","price":"818.95","nrml":"234690","mis":"117345","co_margin":"122539.49","bo_margin":"122539.49"},{"scrip":"COALINDIA","expiry":"Mar-2021","lot":"4200","price":"150.95","nrml":"149079","mis":"74539.5","co_margin":"76712.79","bo_margin":"76712.79"},{"scrip":"COALINDIA","expiry":"Apr-2021","lot":"4200","price":"151.30","nrml":"149665","mis":"74832.5","co_margin":"76890.66","bo_margin":"76890.66"},{"scrip":"COALINDIA","expiry":"May-2021","lot":"4200","price":"148.45","nrml":"150132","mis":"75066","co_margin":"75442.29","bo_margin":"75442.29"},{"scrip":"COFORGE","expiry":"Mar-2021","lot":"375","price":"2734.10","nrml":"457229","mis":"228614.5","co_margin":"250682.79","bo_margin":"250682.79"},{"scrip":"COFORGE","expiry":"Apr-2021","lot":"375","price":"2740.25","nrml":"458862","mis":"229431","co_margin":"251246.67","bo_margin":"251246.67"},{"scrip":"COFORGE","expiry":"May-2021","lot":"375","price":"2756.20","nrml":"459187","mis":"229593.5","co_margin":"252709.09","bo_margin":"252709.09"},{"scrip":"COLPAL","expiry":"Mar-2021","lot":"700","price":"1647.55","nrml":"214795","mis":"107397.5","co_margin":"112099.3","bo_margin":"112099.3"},{"scrip":"COLPAL","expiry":"Apr-2021","lot":"700","price":"1651.25","nrml":"215679","mis":"107839.5","co_margin":"112351.05","bo_margin":"112351.05"},{"scrip":"COLPAL","expiry":"May-2021","lot":"700","price":"1659.35","nrml":"216011","mis":"108005.5","co_margin":"112902.17","bo_margin":"112902.17"},{"scrip":"CONCOR","expiry":"Mar-2021","lot":"1563","price":"573.80","nrml":"307289","mis":"153644.5","co_margin":"160984.47","bo_margin":"160984.47"},{"scrip":"CONCOR","expiry":"Apr-2021","lot":"1563","price":"575.10","nrml":"308505","mis":"154252.5","co_margin":"161349.19","bo_margin":"161349.19"},{"scrip":"CONCOR","expiry":"May-2021","lot":"1563","price":"578.45","nrml":"311575","mis":"155787.5","co_margin":"162289.06","bo_margin":"162289.06"},{"scrip":"CUB","expiry":"Mar-2021","lot":"3100","price":"172.40","nrml":"141140","mis":"70570","co_margin":"75249.15","bo_margin":"75249.15"},{"scrip":"CUB","expiry":"Apr-2021","lot":"3100","price":"172.80","nrml":"141710","mis":"70855","co_margin":"75423.74","bo_margin":"75423.74"},{"scrip":"CUB","expiry":"May-2021","lot":"3100","price":"173.80","nrml":"142212","mis":"71106","co_margin":"75860.22","bo_margin":"75860.22"},{"scrip":"CUMMINSIND","expiry":"Mar-2021","lot":"1200","price":"879.35","nrml":"243342","mis":"121671","co_margin":"130319.67","bo_margin":"130319.67"},{"scrip":"CUMMINSIND","expiry":"Apr-2021","lot":"1200","price":"881.35","nrml":"244098","mis":"122049","co_margin":"130616.07","bo_margin":"130616.07"},{"scrip":"CUMMINSIND","expiry":"May-2021","lot":"1200","price":"886.45","nrml":"241901","mis":"120950.5","co_margin":"131371.89","bo_margin":"131371.89"},{"scrip":"DABUR","expiry":"Mar-2021","lot":"1250","price":"531.15","nrml":"116961","mis":"58480.5","co_margin":"60219.13","bo_margin":"60219.13"},{"scrip":"DABUR","expiry":"Apr-2021","lot":"1250","price":"532.35","nrml":"117414","mis":"58707","co_margin":"60355.18","bo_margin":"60355.18"},{"scrip":"DABUR","expiry":"May-2021","lot":"1250","price":"538.25","nrml":"117781","mis":"58890.5","co_margin":"61024.09","bo_margin":"61024.09"},{"scrip":"DEEPAKNTR","expiry":"Mar-2021","lot":"500","price":"1599.30","nrml":"241022","mis":"120511","co_margin":"129623.27","bo_margin":"129623.27"},{"scrip":"DEEPAKNTR","expiry":"Apr-2021","lot":"500","price":"1602.90","nrml":"241910","mis":"120955","co_margin":"129915.05","bo_margin":"129915.05"},{"scrip":"DEEPAKNTR","expiry":"May-2021","lot":"500","price":"1622.40","nrml":"242636","mis":"121318","co_margin":"131495.52","bo_margin":"131495.52"},{"scrip":"DIVISLAB","expiry":"Mar-2021","lot":"200","price":"3528.10","nrml":"147523","mis":"73761.5","co_margin":"76136.4","bo_margin":"76136.4"},{"scrip":"DIVISLAB","expiry":"Apr-2021","lot":"200","price":"3536.00","nrml":"148105","mis":"74052.5","co_margin":"76306.88","bo_margin":"76306.88"},{"scrip":"DIVISLAB","expiry":"May-2021","lot":"200","price":"3556.60","nrml":"148466","mis":"74233","co_margin":"76751.43","bo_margin":"76751.43"},{"scrip":"DLF","expiry":"Mar-2021","lot":"3300","price":"314.25","nrml":"317780","mis":"158890","co_margin":"167375.84","bo_margin":"167375.84"},{"scrip":"DLF","expiry":"Apr-2021","lot":"3300","price":"314.95","nrml":"318932","mis":"159466","co_margin":"167748.67","bo_margin":"167748.67"},{"scrip":"DLF","expiry":"May-2021","lot":"3300","price":"316.80","nrml":"319676","mis":"159838","co_margin":"168734.02","bo_margin":"168734.02"},{"scrip":"DRREDDY","expiry":"Mar-2021","lot":"125","price":"4500.35","nrml":"109530","mis":"54765","co_margin":"57548.23","bo_margin":"57548.23"},{"scrip":"DRREDDY","expiry":"Apr-2021","lot":"125","price":"4510.45","nrml":"109946","mis":"54973","co_margin":"57677.38","bo_margin":"57677.38"},{"scrip":"DRREDDY","expiry":"May-2021","lot":"125","price":"4575.40","nrml":"110324","mis":"55162","co_margin":"58507.93","bo_margin":"58507.93"},{"scrip":"EICHERMOT","expiry":"Mar-2021","lot":"350","price":"2672.30","nrml":"222153","mis":"111076.5","co_margin":"117474.31","bo_margin":"117474.31"},{"scrip":"EICHERMOT","expiry":"Apr-2021","lot":"350","price":"2678.30","nrml":"222963","mis":"111481.5","co_margin":"117738.07","bo_margin":"117738.07"},{"scrip":"EICHERMOT","expiry":"May-2021","lot":"350","price":"2693.90","nrml":"223552","mis":"111776","co_margin":"118423.84","bo_margin":"118423.84"},{"scrip":"ESCORTS","expiry":"Mar-2021","lot":"550","price":"1365.05","nrml":"209349","mis":"104674.5","co_margin":"110364.29","bo_margin":"110364.29"},{"scrip":"ESCORTS","expiry":"Apr-2021","lot":"550","price":"1368.15","nrml":"210141","mis":"105070.5","co_margin":"110614.93","bo_margin":"110614.93"},{"scrip":"ESCORTS","expiry":"May-2021","lot":"550","price":"1376.10","nrml":"210268","mis":"105134","co_margin":"111257.69","bo_margin":"111257.69"},{"scrip":"EXIDEIND","expiry":"Mar-2021","lot":"3600","price":"202.75","nrml":"192922","mis":"96461","co_margin":"101018.16","bo_margin":"101018.16"},{"scrip":"EXIDEIND","expiry":"Apr-2021","lot":"3600","price":"203.20","nrml":"193698","mis":"96849","co_margin":"101242.37","bo_margin":"101242.37"},{"scrip":"EXIDEIND","expiry":"May-2021","lot":"3600","price":"204.40","nrml":"194636","mis":"97318","co_margin":"101840.26","bo_margin":"101840.26"},{"scrip":"FEDERALBNK","expiry":"Mar-2021","lot":"10000","price":"86.30","nrml":"261160","mis":"130580","co_margin":"140582.7","bo_margin":"140582.7"},{"scrip":"FEDERALBNK","expiry":"Apr-2021","lot":"10000","price":"86.50","nrml":"262100","mis":"131050","co_margin":"140908.5","bo_margin":"140908.5"},{"scrip":"FEDERALBNK","expiry":"May-2021","lot":"10000","price":"87.80","nrml":"262835","mis":"131417.5","co_margin":"143026.2","bo_margin":"143026.2"},{"scrip":"FINNIFTY","expiry":"Mar-2021","lot":"40","price":"16689.70","nrml":"130149","mis":"65074.5","co_margin":"67626.66","bo_margin":"67626.66"},{"scrip":"FINNIFTY","expiry":"Apr-2021","lot":"40","price":"16727.10","nrml":"130604","mis":"65302","co_margin":"67778.21","bo_margin":"67778.21"},{"scrip":"FINNIFTY","expiry":"May-2021","lot":"40","price":"16788.00","nrml":"130728","mis":"65364","co_margin":"68024.98","bo_margin":"68024.98"},{"scrip":"GAIL","expiry":"Mar-2021","lot":"6100","price":"147.70","nrml":"372813","mis":"186406.5","co_margin":"195870.88","bo_margin":"195870.88"},{"scrip":"GAIL","expiry":"Apr-2021","lot":"6100","price":"148.05","nrml":"374190","mis":"187095","co_margin":"196335.03","bo_margin":"196335.03"},{"scrip":"GAIL","expiry":"May-2021","lot":"6100","price":"148.90","nrml":"375679","mis":"187839.5","co_margin":"197462.25","bo_margin":"197462.25"},{"scrip":"GLENMARK","expiry":"Mar-2021","lot":"1150","price":"486.50","nrml":"219303","mis":"109651.5","co_margin":"117713.54","bo_margin":"117713.54"},{"scrip":"GLENMARK","expiry":"Apr-2021","lot":"1150","price":"487.60","nrml":"220130","mis":"110065","co_margin":"117979.7","bo_margin":"117979.7"},{"scrip":"GLENMARK","expiry":"May-2021","lot":"1150","price":"494.00","nrml":"220800","mis":"110400","co_margin":"119528.24","bo_margin":"119528.24"},{"scrip":"GMRINFRA","expiry":"Mar-2021","lot":"22500","price":"27.90","nrml":"171039","mis":"85519.5","co_margin":"91839.83","bo_margin":"91839.83"},{"scrip":"GMRINFRA","expiry":"Apr-2021","lot":"22500","price":"28.00","nrml":"171568","mis":"85784","co_margin":"92169","bo_margin":"92169"},{"scrip":"GMRINFRA","expiry":"May-2021","lot":"22500","price":"28.15","nrml":"172530","mis":"86265","co_margin":"92662.76","bo_margin":"92662.76"},{"scrip":"GODREJCP","expiry":"Mar-2021","lot":"1000","price":"694.30","nrml":"154022","mis":"77011","co_margin":"80538.8","bo_margin":"80538.8"},{"scrip":"GODREJCP","expiry":"Apr-2021","lot":"1000","price":"695.85","nrml":"154690","mis":"77345","co_margin":"80718.6","bo_margin":"80718.6"},{"scrip":"GODREJCP","expiry":"May-2021","lot":"1000","price":"699.90","nrml":"155090","mis":"77545","co_margin":"81188.4","bo_margin":"81188.4"},{"scrip":"GODREJPROP","expiry":"Mar-2021","lot":"650","price":"1463.30","nrml":"281678","mis":"140839","co_margin":"148854.19","bo_margin":"148854.19"},{"scrip":"GODREJPROP","expiry":"Apr-2021","lot":"650","price":"1466.60","nrml":"282734","mis":"141367","co_margin":"149189.89","bo_margin":"149189.89"},{"scrip":"GODREJPROP","expiry":"May-2021","lot":"650","price":"1475.15","nrml":"283972","mis":"141986","co_margin":"150059.63","bo_margin":"150059.63"},{"scrip":"GRANULES","expiry":"Mar-2021","lot":"1550","price":"350.35","nrml":"161258","mis":"80629","co_margin":"88353.01","bo_margin":"88353.01"},{"scrip":"GRANULES","expiry":"Apr-2021","lot":"1550","price":"351.15","nrml":"161851","mis":"80925.5","co_margin":"88554.76","bo_margin":"88554.76"},{"scrip":"GRANULES","expiry":"May-2021","lot":"1550","price":"353.20","nrml":"162464","mis":"81232","co_margin":"89071.74","bo_margin":"89071.74"},{"scrip":"GRASIM","expiry":"Mar-2021","lot":"950","price":"1385.05","nrml":"327788","mis":"163894","co_margin":"174211.59","bo_margin":"174211.59"},{"scrip":"GRASIM","expiry":"Apr-2021","lot":"950","price":"1388.15","nrml":"329020","mis":"164510","co_margin":"174601.51","bo_margin":"174601.51"},{"scrip":"GRASIM","expiry":"May-2021","lot":"950","price":"1396.25","nrml":"329575","mis":"164787.5","co_margin":"175620.33","bo_margin":"175620.33"},{"scrip":"GUJGASLTD","expiry":"Mar-2021","lot":"1250","price":"534.65","nrml":"166824","mis":"83412","co_margin":"85878.16","bo_margin":"85878.16"},{"scrip":"GUJGASLTD","expiry":"Apr-2021","lot":"1250","price":"535.85","nrml":"167663","mis":"83831.5","co_margin":"86070.91","bo_margin":"86070.91"},{"scrip":"GUJGASLTD","expiry":"May-2021","lot":"1250","price":"539.00","nrml":"167849","mis":"83924.5","co_margin":"86576.88","bo_margin":"86576.88"},{"scrip":"HAVELLS","expiry":"Mar-2021","lot":"1000","price":"1120.30","nrml":"268060","mis":"134030","co_margin":"145190.88","bo_margin":"145190.88"},{"scrip":"HAVELLS","expiry":"Apr-2021","lot":"1000","price":"1122.85","nrml":"269214","mis":"134607","co_margin":"145521.36","bo_margin":"145521.36"},{"scrip":"HAVELLS","expiry":"May-2021","lot":"1000","price":"1129.35","nrml":"269597","mis":"134798.5","co_margin":"146363.76","bo_margin":"146363.76"},{"scrip":"HCLTECH","expiry":"Mar-2021","lot":"700","price":"988.50","nrml":"160535","mis":"80267.5","co_margin":"84763.88","bo_margin":"84763.88"},{"scrip":"HCLTECH","expiry":"Apr-2021","lot":"700","price":"990.75","nrml":"161175","mis":"80587.5","co_margin":"84956.81","bo_margin":"84956.81"},{"scrip":"HCLTECH","expiry":"May-2021","lot":"700","price":"1001.30","nrml":"161696","mis":"80848","co_margin":"85861.48","bo_margin":"85861.48"},{"scrip":"HDFC","expiry":"Mar-2021","lot":"300","price":"2599.80","nrml":"200720","mis":"100360","co_margin":"106227.83","bo_margin":"106227.83"},{"scrip":"HDFC","expiry":"Apr-2021","lot":"300","price":"2605.65","nrml":"201475","mis":"100737.5","co_margin":"106466.86","bo_margin":"106466.86"},{"scrip":"HDFC","expiry":"May-2021","lot":"300","price":"2628.75","nrml":"202105","mis":"101052.5","co_margin":"107410.73","bo_margin":"107410.73"},{"scrip":"HDFCAMC","expiry":"Mar-2021","lot":"200","price":"3118.50","nrml":"148643","mis":"74321.5","co_margin":"76839.84","bo_margin":"76839.84"},{"scrip":"HDFCAMC","expiry":"Apr-2021","lot":"200","price":"3125.50","nrml":"149225","mis":"74612.5","co_margin":"77012.32","bo_margin":"77012.32"},{"scrip":"HDFCAMC","expiry":"May-2021","lot":"200","price":"3143.70","nrml":"150177","mis":"75088.5","co_margin":"77460.77","bo_margin":"77460.77"},{"scrip":"HDFCBANK","expiry":"Mar-2021","lot":"550","price":"1555.75","nrml":"180747","mis":"90373.5","co_margin":"93267.21","bo_margin":"93267.21"},{"scrip":"HDFCBANK","expiry":"Apr-2021","lot":"550","price":"1559.25","nrml":"181405","mis":"90702.5","co_margin":"93477.04","bo_margin":"93477.04"},{"scrip":"HDFCBANK","expiry":"May-2021","lot":"550","price":"1574.35","nrml":"181979","mis":"90989.5","co_margin":"94382.28","bo_margin":"94382.28"},{"scrip":"HDFCLIFE","expiry":"Mar-2021","lot":"1100","price":"731.35","nrml":"197070","mis":"98535","co_margin":"102089.15","bo_margin":"102089.15"},{"scrip":"HDFCLIFE","expiry":"Apr-2021","lot":"1100","price":"733.00","nrml":"197880","mis":"98940","co_margin":"102319.47","bo_margin":"102319.47"},{"scrip":"HDFCLIFE","expiry":"May-2021","lot":"1100","price":"737.25","nrml":"198453","mis":"99226.5","co_margin":"102912.73","bo_margin":"102912.73"},{"scrip":"HEROMOTOCO","expiry":"Mar-2021","lot":"300","price":"3419.35","nrml":"245244","mis":"122622","co_margin":"127199.82","bo_margin":"127199.82"},{"scrip":"HEROMOTOCO","expiry":"Apr-2021","lot":"300","price":"3427.00","nrml":"245919","mis":"122959.5","co_margin":"127484.4","bo_margin":"127484.4"},{"scrip":"HEROMOTOCO","expiry":"May-2021","lot":"300","price":"3446.95","nrml":"246858","mis":"123429","co_margin":"128226.54","bo_margin":"128226.54"},{"scrip":"HINDALCO","expiry":"Mar-2021","lot":"4300","price":"340.35","nrml":"434713","mis":"217356.5","co_margin":"234014.45","bo_margin":"234014.45"},{"scrip":"HINDALCO","expiry":"Apr-2021","lot":"4300","price":"341.15","nrml":"436225","mis":"218112.5","co_margin":"234564.51","bo_margin":"234564.51"},{"scrip":"HINDALCO","expiry":"May-2021","lot":"4300","price":"343.10","nrml":"437516","mis":"218758","co_margin":"235905.27","bo_margin":"235905.27"},{"scrip":"HINDPETRO","expiry":"Mar-2021","lot":"2700","price":"241.00","nrml":"223773","mis":"111886.5","co_margin":"117386.28","bo_margin":"117386.28"},{"scrip":"HINDPETRO","expiry":"Apr-2021","lot":"2700","price":"241.55","nrml":"224625","mis":"112312.5","co_margin":"117654.17","bo_margin":"117654.17"},{"scrip":"HINDPETRO","expiry":"May-2021","lot":"2700","price":"242.95","nrml":"225367","mis":"112683.5","co_margin":"118336.09","bo_margin":"118336.09"},{"scrip":"HINDUNILVR","expiry":"Mar-2021","lot":"300","price":"2227.85","nrml":"119444","mis":"59722","co_margin":"62357.52","bo_margin":"62357.52"},{"scrip":"HINDUNILVR","expiry":"Apr-2021","lot":"300","price":"2232.85","nrml":"119918","mis":"59959","co_margin":"62497.47","bo_margin":"62497.47"},{"scrip":"HINDUNILVR","expiry":"May-2021","lot":"300","price":"2257.35","nrml":"120329","mis":"60164.5","co_margin":"63183.23","bo_margin":"63183.23"},{"scrip":"IBULHSGFIN","expiry":"Mar-2021","lot":"3100","price":"230.20","nrml":"381129","mis":"190564.5","co_margin":"212872.85","bo_margin":"212872.85"},{"scrip":"IBULHSGFIN","expiry":"Apr-2021","lot":"3100","price":"230.75","nrml":"382377","mis":"191188.5","co_margin":"213381.45","bo_margin":"213381.45"},{"scrip":"IBULHSGFIN","expiry":"May-2021","lot":"3100","price":"232.10","nrml":"384252","mis":"192126","co_margin":"214629.83","bo_margin":"214629.83"},{"scrip":"ICICIBANK","expiry":"Mar-2021","lot":"1375","price":"625.60","nrml":"241693","mis":"120846.5","co_margin":"126793.48","bo_margin":"126793.48"},{"scrip":"ICICIBANK","expiry":"Apr-2021","lot":"1375","price":"627.00","nrml":"242618","mis":"121309","co_margin":"127077.23","bo_margin":"127077.23"},{"scrip":"ICICIBANK","expiry":"May-2021","lot":"1375","price":"634.30","nrml":"243340","mis":"121670","co_margin":"128556.75","bo_margin":"128556.75"},{"scrip":"ICICIGI","expiry":"Mar-2021","lot":"425","price":"1471.10","nrml":"152215","mis":"76107.5","co_margin":"79090.01","bo_margin":"79090.01"},{"scrip":"ICICIGI","expiry":"Apr-2021","lot":"425","price":"1474.40","nrml":"152928","mis":"76464","co_margin":"79267.43","bo_margin":"79267.43"},{"scrip":"ICICIGI","expiry":"May-2021","lot":"425","price":"1483.00","nrml":"153674","mis":"76837","co_margin":"79729.79","bo_margin":"79729.79"},{"scrip":"ICICIPRULI","expiry":"Mar-2021","lot":"1500","price":"484.00","nrml":"251179","mis":"125589.5","co_margin":"131696.4","bo_margin":"131696.4"},{"scrip":"ICICIPRULI","expiry":"Apr-2021","lot":"1500","price":"485.10","nrml":"252123","mis":"126061.5","co_margin":"131995.71","bo_margin":"131995.71"},{"scrip":"ICICIPRULI","expiry":"May-2021","lot":"1500","price":"487.90","nrml":"252382","mis":"126191","co_margin":"132757.59","bo_margin":"132757.59"},{"scrip":"IDEA","expiry":"Mar-2021","lot":"70000","price":"10.30","nrml":"440772","mis":"220386","co_margin":"232955.1","bo_margin":"232955.1"},{"scrip":"IDEA","expiry":"Apr-2021","lot":"70000","price":"10.35","nrml":"443275","mis":"221637.5","co_margin":"234085.95","bo_margin":"234085.95"},{"scrip":"IDEA","expiry":"May-2021","lot":"70000","price":"10.40","nrml":"444342","mis":"222171","co_margin":"235216.8","bo_margin":"235216.8"},{"scrip":"IDFCFIRSTB","expiry":"Mar-2021","lot":"19000","price":"66.85","nrml":"597412","mis":"298706","co_margin":"313218.99","bo_margin":"313218.99"},{"scrip":"IDFCFIRSTB","expiry":"Apr-2021","lot":"19000","price":"67.00","nrml":"599070","mis":"299535","co_margin":"313921.8","bo_margin":"313921.8"},{"scrip":"IDFCFIRSTB","expiry":"May-2021","lot":"19000","price":"65.95","nrml":"600490","mis":"300245","co_margin":"309002.13","bo_margin":"309002.13"},{"scrip":"IGL","expiry":"Mar-2021","lot":"1375","price":"510.60","nrml":"170026","mis":"85013","co_margin":"86987.09","bo_margin":"86987.09"},{"scrip":"IGL","expiry":"Apr-2021","lot":"1375","price":"511.75","nrml":"170685","mis":"85342.5","co_margin":"87183.01","bo_margin":"87183.01"},{"scrip":"IGL","expiry":"May-2021","lot":"1375","price":"514.75","nrml":"171238","mis":"85619","co_margin":"87694.1","bo_margin":"87694.1"},{"scrip":"INDIGO","expiry":"Mar-2021","lot":"500","price":"1684.55","nrml":"237933","mis":"118966.5","co_margin":"125246.29","bo_margin":"125246.29"},{"scrip":"INDIGO","expiry":"Apr-2021","lot":"500","price":"1688.35","nrml":"238762","mis":"119381","co_margin":"125528.82","bo_margin":"125528.82"},{"scrip":"INDIGO","expiry":"May-2021","lot":"500","price":"1698.15","nrml":"239500","mis":"119750","co_margin":"126257.45","bo_margin":"126257.45"},{"scrip":"INDUSINDBK","expiry":"Mar-2021","lot":"900","price":"1039.85","nrml":"479189","mis":"239594.5","co_margin":"260825.58","bo_margin":"260825.58"},{"scrip":"INDUSINDBK","expiry":"Apr-2021","lot":"900","price":"1042.20","nrml":"480934","mis":"240467","co_margin":"261415.03","bo_margin":"261415.03"},{"scrip":"INDUSINDBK","expiry":"May-2021","lot":"900","price":"1048.25","nrml":"482147","mis":"241073.5","co_margin":"262932.55","bo_margin":"262932.55"},{"scrip":"INDUSTOWER","expiry":"Mar-2021","lot":"2800","price":"254.80","nrml":"247916","mis":"123958","co_margin":"133056.56","bo_margin":"133056.56"},{"scrip":"INDUSTOWER","expiry":"Apr-2021","lot":"2800","price":"255.40","nrml":"248754","mis":"124377","co_margin":"133369.88","bo_margin":"133369.88"},{"scrip":"INDUSTOWER","expiry":"May-2021","lot":"2800","price":"256.90","nrml":"248943","mis":"124471.5","co_margin":"134153.18","bo_margin":"134153.18"},{"scrip":"INFY","expiry":"Mar-2021","lot":"600","price":"1368.15","nrml":"173256","mis":"86628","co_margin":"91447.15","bo_margin":"91447.15"},{"scrip":"INFY","expiry":"Apr-2021","lot":"600","price":"1371.25","nrml":"173923","mis":"86961.5","co_margin":"91654.35","bo_margin":"91654.35"},{"scrip":"INFY","expiry":"May-2021","lot":"600","price":"1385.60","nrml":"174484","mis":"87242","co_margin":"92613.5","bo_margin":"92613.5"},{"scrip":"IOC","expiry":"Mar-2021","lot":"6500","price":"98.85","nrml":"139288","mis":"69644","co_margin":"72027.05","bo_margin":"72027.05"},{"scrip":"IOC","expiry":"Apr-2021","lot":"6500","price":"99.10","nrml":"139815","mis":"69907.5","co_margin":"72209.22","bo_margin":"72209.22"},{"scrip":"IOC","expiry":"May-2021","lot":"6500","price":"100.55","nrml":"140265","mis":"70132.5","co_margin":"73265.76","bo_margin":"73265.76"},{"scrip":"IRCTC","expiry":"Mar-2021","lot":"325","price":"2018.45","nrml":"162027","mis":"81013.5","co_margin":"84426.72","bo_margin":"84426.72"},{"scrip":"IRCTC","expiry":"Apr-2021","lot":"325","price":"2023.00","nrml":"162687","mis":"81343.5","co_margin":"84617.03","bo_margin":"84617.03"},{"scrip":"IRCTC","expiry":"May-2021","lot":"325","price":"2048.80","nrml":"163124","mis":"81562","co_margin":"85696.18","bo_margin":"85696.18"},{"scrip":"ITC","expiry":"Mar-2021","lot":"3200","price":"206.50","nrml":"145517","mis":"72758.5","co_margin":"73943.52","bo_margin":"73943.52"},{"scrip":"ITC","expiry":"Apr-2021","lot":"3200","price":"207.00","nrml":"146111","mis":"73055.5","co_margin":"74122.56","bo_margin":"74122.56"},{"scrip":"ITC","expiry":"May-2021","lot":"3200","price":"209.75","nrml":"146558","mis":"73279","co_margin":"75107.28","bo_margin":"75107.28"},{"scrip":"JINDALSTEL","expiry":"Mar-2021","lot":"5000","price":"320.35","nrml":"567110","mis":"283555","co_margin":"304012.15","bo_margin":"304012.15"},{"scrip":"JINDALSTEL","expiry":"Apr-2021","lot":"5000","price":"321.10","nrml":"569231","mis":"284615.5","co_margin":"304723.9","bo_margin":"304723.9"},{"scrip":"JINDALSTEL","expiry":"May-2021","lot":"5000","price":"322.95","nrml":"572518","mis":"286259","co_margin":"306479.55","bo_margin":"306479.55"},{"scrip":"JSWSTEEL","expiry":"Mar-2021","lot":"2700","price":"414.00","nrml":"290205","mis":"145102.5","co_margin":"156603.78","bo_margin":"156603.78"},{"scrip":"JSWSTEEL","expiry":"Apr-2021","lot":"2700","price":"414.95","nrml":"291280","mis":"145640","co_margin":"156963.14","bo_margin":"156963.14"},{"scrip":"JSWSTEEL","expiry":"May-2021","lot":"2700","price":"417.35","nrml":"290965","mis":"145482.5","co_margin":"157870.98","bo_margin":"157870.98"},{"scrip":"JUBLFOOD","expiry":"Mar-2021","lot":"250","price":"3001.55","nrml":"314500","mis":"157250","co_margin":"164484.94","bo_margin":"164484.94"},{"scrip":"JUBLFOOD","expiry":"Apr-2021","lot":"250","price":"3008.30","nrml":"315629","mis":"157814.5","co_margin":"164854.84","bo_margin":"164854.84"},{"scrip":"JUBLFOOD","expiry":"May-2021","lot":"250","price":"3025.80","nrml":"316993","mis":"158496.5","co_margin":"165813.84","bo_margin":"165813.84"},{"scrip":"KOTAKBANK","expiry":"Mar-2021","lot":"400","price":"1963.95","nrml":"225063","mis":"112531.5","co_margin":"118308.35","bo_margin":"118308.35"},{"scrip":"KOTAKBANK","expiry":"Apr-2021","lot":"400","price":"1968.35","nrml":"225858","mis":"112929","co_margin":"118573.4","bo_margin":"118573.4"},{"scrip":"KOTAKBANK","expiry":"May-2021","lot":"400","price":"1969.70","nrml":"226471","mis":"113235.5","co_margin":"118654.73","bo_margin":"118654.73"},{"scrip":"L&TFH","expiry":"Mar-2021","lot":"8300","price":"106.00","nrml":"283023","mis":"141511.5","co_margin":"149566","bo_margin":"149566"},{"scrip":"L&TFH","expiry":"Apr-2021","lot":"8924","price":"106.25","nrml":"305412","mis":"152706","co_margin":"161189.75","bo_margin":"161189.75"},{"scrip":"L&TFH","expiry":"May-2021","lot":"8924","price":"107.50","nrml":"306293","mis":"153146.5","co_margin":"163086.1","bo_margin":"163086.1"},{"scrip":"LALPATHLAB","expiry":"Mar-2021","lot":"250","price":"2350.10","nrml":"146256","mis":"73128","co_margin":"75555.72","bo_margin":"75555.72"},{"scrip":"LALPATHLAB","expiry":"Apr-2021","lot":"250","price":"2355.40","nrml":"146827","mis":"73413.5","co_margin":"75726.11","bo_margin":"75726.11"},{"scrip":"LALPATHLAB","expiry":"May-2021","lot":"250","price":"2369.10","nrml":"146955","mis":"73477.5","co_margin":"76166.57","bo_margin":"76166.57"},{"scrip":"LICHSGFIN","expiry":"Mar-2021","lot":"2000","price":"433.15","nrml":"262910","mis":"131455","co_margin":"138521.37","bo_margin":"138521.37"},{"scrip":"LICHSGFIN","expiry":"Apr-2021","lot":"2000","price":"434.15","nrml":"263918","mis":"131959","co_margin":"138841.17","bo_margin":"138841.17"},{"scrip":"LICHSGFIN","expiry":"May-2021","lot":"2000","price":"436.65","nrml":"264550","mis":"132275","co_margin":"139640.67","bo_margin":"139640.67"},{"scrip":"LT","expiry":"Mar-2021","lot":"575","price":"1524.20","nrml":"192504","mis":"96252","co_margin":"100612.44","bo_margin":"100612.44"},{"scrip":"LT","expiry":"Apr-2021","lot":"575","price":"1527.65","nrml":"193227","mis":"96613.5","co_margin":"100840.18","bo_margin":"100840.18"},{"scrip":"LT","expiry":"May-2021","lot":"575","price":"1542.55","nrml":"193791","mis":"96895.5","co_margin":"101823.73","bo_margin":"101823.73"},{"scrip":"LTI","expiry":"Mar-2021","lot":"150","price":"4129.05","nrml":"151562","mis":"75781","co_margin":"83489.39","bo_margin":"83489.39"},{"scrip":"LTI","expiry":"Apr-2021","lot":"150","price":"4138.30","nrml":"152114","mis":"76057","co_margin":"83676.43","bo_margin":"83676.43"},{"scrip":"LTI","expiry":"May-2021","lot":"150","price":"4162.40","nrml":"150928","mis":"75464","co_margin":"84163.73","bo_margin":"84163.73"},{"scrip":"LTTS","expiry":"Mar-2021","lot":"200","price":"2759.85","nrml":"148181","mis":"74090.5","co_margin":"77220.6","bo_margin":"77220.6"},{"scrip":"LTTS","expiry":"Apr-2021","lot":"200","price":"2766.05","nrml":"148810","mis":"74405","co_margin":"77394.08","bo_margin":"77394.08"},{"scrip":"LTTS","expiry":"May-2021","lot":"200","price":"2782.15","nrml":"148010","mis":"74005","co_margin":"77844.56","bo_margin":"77844.56"},{"scrip":"LUPIN","expiry":"Mar-2021","lot":"850","price":"1057.70","nrml":"200625","mis":"100312.5","co_margin":"105457.98","bo_margin":"105457.98"},{"scrip":"LUPIN","expiry":"Apr-2021","lot":"850","price":"1060.10","nrml":"201373","mis":"100686.5","co_margin":"105697.27","bo_margin":"105697.27"},{"scrip":"LUPIN","expiry":"May-2021","lot":"850","price":"1072.00","nrml":"202054","mis":"101027","co_margin":"106883.76","bo_margin":"106883.76"},{"scrip":"M&M","expiry":"Mar-2021","lot":"1400","price":"863.80","nrml":"361447","mis":"180723.5","co_margin":"193612.13","bo_margin":"193612.13"},{"scrip":"M&M","expiry":"Apr-2021","lot":"1400","price":"865.75","nrml":"362776","mis":"181388","co_margin":"194049.21","bo_margin":"194049.21"},{"scrip":"M&M","expiry":"May-2021","lot":"1400","price":"870.80","nrml":"364117","mis":"182058.5","co_margin":"195181.11","bo_margin":"195181.11"},{"scrip":"M&MFIN","expiry":"Mar-2021","lot":"4000","price":"211.55","nrml":"293440","mis":"146720","co_margin":"159085.6","bo_margin":"159085.6"},{"scrip":"M&MFIN","expiry":"Apr-2021","lot":"4000","price":"212.05","nrml":"294582","mis":"147291","co_margin":"159461.6","bo_margin":"159461.6"},{"scrip":"M&MFIN","expiry":"May-2021","lot":"4000","price":"213.90","nrml":"295426","mis":"147713","co_margin":"160852.8","bo_margin":"160852.8"},{"scrip":"MANAPPURAM","expiry":"Mar-2021","lot":"6000","price":"162.60","nrml":"308616","mis":"154308","co_margin":"165266.64","bo_margin":"165266.64"},{"scrip":"MANAPPURAM","expiry":"Apr-2021","lot":"6000","price":"163.00","nrml":"309772","mis":"154886","co_margin":"165673.2","bo_margin":"165673.2"},{"scrip":"MANAPPURAM","expiry":"May-2021","lot":"6000","price":"165.25","nrml":"310773","mis":"155386.5","co_margin":"167960.1","bo_margin":"167960.1"},{"scrip":"MARICO","expiry":"Mar-2021","lot":"2000","price":"399.25","nrml":"142405","mis":"71202.5","co_margin":"72583.65","bo_margin":"72583.65"},{"scrip":"MARICO","expiry":"Apr-2021","lot":"2000","price":"400.15","nrml":"142982","mis":"71491","co_margin":"72747.27","bo_margin":"72747.27"},{"scrip":"MARICO","expiry":"May-2021","lot":"2000","price":"402.50","nrml":"143113","mis":"71556.5","co_margin":"73174.5","bo_margin":"73174.5"},{"scrip":"MARUTI","expiry":"Mar-2021","lot":"100","price":"7272.20","nrml":"192979","mis":"96489.5","co_margin":"99774.58","bo_margin":"99774.58"},{"scrip":"MARUTI","expiry":"Apr-2021","lot":"100","price":"7288.50","nrml":"193749","mis":"96874.5","co_margin":"99998.22","bo_margin":"99998.22"},{"scrip":"MARUTI","expiry":"May-2021","lot":"100","price":"7330.90","nrml":"194447","mis":"97223.5","co_margin":"100579.95","bo_margin":"100579.95"},{"scrip":"MCDOWELL-N","expiry":"Mar-2021","lot":"1250","price":"553.25","nrml":"151580","mis":"75790","co_margin":"78630.66","bo_margin":"78630.66"},{"scrip":"MCDOWELL-N","expiry":"Apr-2021","lot":"1250","price":"554.50","nrml":"152178","mis":"76089","co_margin":"78808.31","bo_margin":"78808.31"},{"scrip":"MCDOWELL-N","expiry":"May-2021","lot":"1250","price":"562.40","nrml":"152737","mis":"76368.5","co_margin":"79931.1","bo_margin":"79931.1"},{"scrip":"MFSL","expiry":"Mar-2021","lot":"1300","price":"931.40","nrml":"384949","mis":"192474.5","co_margin":"201722.61","bo_margin":"201722.61"},{"scrip":"MFSL","expiry":"Apr-2021","lot":"1300","price":"933.50","nrml":"386542","mis":"193271","co_margin":"202177.43","bo_margin":"202177.43"},{"scrip":"MFSL","expiry":"May-2021","lot":"1300","price":"938.95","nrml":"385591","mis":"192795.5","co_margin":"203357.79","bo_margin":"203357.79"},{"scrip":"MGL","expiry":"Mar-2021","lot":"600","price":"1169.15","nrml":"173800","mis":"86900","co_margin":"90001.17","bo_margin":"90001.17"},{"scrip":"MGL","expiry":"Apr-2021","lot":"600","price":"1171.80","nrml":"174439","mis":"87219.5","co_margin":"90205.16","bo_margin":"90205.16"},{"scrip":"MGL","expiry":"May-2021","lot":"600","price":"1178.60","nrml":"175053","mis":"87526.5","co_margin":"90728.63","bo_margin":"90728.63"},{"scrip":"MINDTREE","expiry":"Mar-2021","lot":"800","price":"1892.45","nrml":"396792","mis":"198396","co_margin":"213468.36","bo_margin":"213468.36"},{"scrip":"MINDTREE","expiry":"Apr-2021","lot":"800","price":"1896.70","nrml":"398169","mis":"199084.5","co_margin":"213947.76","bo_margin":"213947.76"},{"scrip":"MINDTREE","expiry":"May-2021","lot":"800","price":"1907.75","nrml":"391167","mis":"195583.5","co_margin":"215194.2","bo_margin":"215194.2"},{"scrip":"MOTHERSUMI","expiry":"Mar-2021","lot":"7000","price":"219.00","nrml":"526151","mis":"263075.5","co_margin":"281918.7","bo_margin":"281918.7"},{"scrip":"MOTHERSUMI","expiry":"Apr-2021","lot":"7000","price":"219.50","nrml":"528052","mis":"264026","co_margin":"282562.35","bo_margin":"282562.35"},{"scrip":"MOTHERSUMI","expiry":"May-2021","lot":"7000","price":"220.80","nrml":"529476","mis":"264738","co_margin":"284235.84","bo_margin":"284235.84"},{"scrip":"MPHASIS","expiry":"Mar-2021","lot":"325","price":"1646.60","nrml":"128751","mis":"64375.5","co_margin":"69889.94","bo_margin":"69889.94"},{"scrip":"MPHASIS","expiry":"Apr-2021","lot":"325","price":"1650.30","nrml":"129466","mis":"64733","co_margin":"70046.98","bo_margin":"70046.98"},{"scrip":"MPHASIS","expiry":"May-2021","lot":"325","price":"1659.90","nrml":"129823","mis":"64911.5","co_margin":"70454.46","bo_margin":"70454.46"},{"scrip":"MRF","expiry":"Mar-2021","lot":"10","price":"88684.40","nrml":"188996","mis":"94498","co_margin":"96488.63","bo_margin":"96488.63"},{"scrip":"MRF","expiry":"Apr-2021","lot":"10","price":"88882.95","nrml":"189672","mis":"94836","co_margin":"96704.65","bo_margin":"96704.65"},{"scrip":"MRF","expiry":"May-2021","lot":"10","price":"89399.90","nrml":"190304","mis":"95152","co_margin":"97267.09","bo_margin":"97267.09"},{"scrip":"MUTHOOTFIN","expiry":"Mar-2021","lot":"750","price":"1304.90","nrml":"260919","mis":"130459.5","co_margin":"138678.25","bo_margin":"138678.25"},{"scrip":"MUTHOOTFIN","expiry":"Apr-2021","lot":"750","price":"1307.85","nrml":"261810","mis":"130905","co_margin":"138991.76","bo_margin":"138991.76"},{"scrip":"MUTHOOTFIN","expiry":"May-2021","lot":"750","price":"1299.30","nrml":"262711","mis":"131355.5","co_margin":"138083.11","bo_margin":"138083.11"},{"scrip":"NAM-INDIA","expiry":"Mar-2021","lot":"1600","price":"353.40","nrml":"170074","mis":"85037","co_margin":"90187.68","bo_margin":"90187.68"},{"scrip":"NAM-INDIA","expiry":"Apr-2021","lot":"1600","price":"354.20","nrml":"170755","mis":"85377.5","co_margin":"90391.84","bo_margin":"90391.84"},{"scrip":"NAM-INDIA","expiry":"May-2021","lot":"1600","price":"356.25","nrml":"171672","mis":"85836","co_margin":"90915","bo_margin":"90915"},{"scrip":"NATIONALUM","expiry":"Mar-2021","lot":"17000","price":"58.70","nrml":"321756","mis":"160878","co_margin":"162458.12","bo_margin":"162458.12"},{"scrip":"NATIONALUM","expiry":"Apr-2021","lot":"17000","price":"58.85","nrml":"323053","mis":"161526.5","co_margin":"162873.26","bo_margin":"162873.26"},{"scrip":"NATIONALUM","expiry":"May-2021","lot":"17000","price":"59.20","nrml":"322394","mis":"161197","co_margin":"163841.92","bo_margin":"163841.92"},{"scrip":"NAUKRI","expiry":"Mar-2021","lot":"250","price":"4869.70","nrml":"353147","mis":"176573.5","co_margin":"183952.92","bo_margin":"183952.92"},{"scrip":"NAUKRI","expiry":"Apr-2021","lot":"250","price":"4880.60","nrml":"354661","mis":"177330.5","co_margin":"184364.67","bo_margin":"184364.67"},{"scrip":"NAUKRI","expiry":"May-2021","lot":"250","price":"4909.00","nrml":"356207","mis":"178103.5","co_margin":"185437.48","bo_margin":"185437.48"},{"scrip":"NAVINFLUOR","expiry":"Mar-2021","lot":"225","price":"2691.05","nrml":"170640","mis":"85320","co_margin":"91791.72","bo_margin":"91791.72"},{"scrip":"NAVINFLUOR","expiry":"Apr-2021","lot":"225","price":"2697.10","nrml":"171392","mis":"85696","co_margin":"91998.08","bo_margin":"91998.08"},{"scrip":"NAVINFLUOR","expiry":"May-2021","lot":"225","price":"2712.80","nrml":"170062","mis":"85031","co_margin":"92533.61","bo_margin":"92533.61"},{"scrip":"NESTLEIND","expiry":"Mar-2021","lot":"50","price":"16932.00","nrml":"160374","mis":"80187","co_margin":"82543.5","bo_margin":"82543.5"},{"scrip":"NESTLEIND","expiry":"Apr-2021","lot":"50","price":"16969.95","nrml":"160880","mis":"80440","co_margin":"82728.51","bo_margin":"82728.51"},{"scrip":"NESTLEIND","expiry":"May-2021","lot":"50","price":"17100.00","nrml":"161450","mis":"80725","co_margin":"83362.5","bo_margin":"83362.5"},{"scrip":"NIFTY","expiry":"Mar-2021","lot":"75","price":"15209.30","nrml":"169002","mis":"84501","co_margin":"88404.06","bo_margin":"88404.06"},{"scrip":"NIFTY","expiry":"Apr-2021","lot":"75","price":"15279.60","nrml":"169639","mis":"84819.5","co_margin":"88812.68","bo_margin":"88812.68"},{"scrip":"NIFTY","expiry":"May-2021","lot":"75","price":"15327.30","nrml":"170133","mis":"85066.5","co_margin":"89089.93","bo_margin":"89089.93"},{"scrip":"NMDC","expiry":"Mar-2021","lot":"6700","price":"132.55","nrml":"282013","mis":"141006.5","co_margin":"150352.79","bo_margin":"150352.79"},{"scrip":"NMDC","expiry":"Apr-2021","lot":"6700","price":"132.85","nrml":"283024","mis":"141512","co_margin":"150693.08","bo_margin":"150693.08"},{"scrip":"NMDC","expiry":"May-2021","lot":"6700","price":"132.50","nrml":"283996","mis":"141998","co_margin":"150296.08","bo_margin":"150296.08"},{"scrip":"NTPC","expiry":"Mar-2021","lot":"5700","price":"109.65","nrml":"150185","mis":"75092.5","co_margin":"78313.13","bo_margin":"78313.13"},{"scrip":"NTPC","expiry":"Apr-2021","lot":"5700","price":"109.90","nrml":"150780","mis":"75390","co_margin":"78491.68","bo_margin":"78491.68"},{"scrip":"NTPC","expiry":"May-2021","lot":"5700","price":"111.20","nrml":"151289","mis":"75644.5","co_margin":"79420.15","bo_margin":"79420.15"},{"scrip":"ONGC","expiry":"Mar-2021","lot":"7700","price":"114.40","nrml":"458096","mis":"229048","co_margin":"240215.98","bo_margin":"240215.98"},{"scrip":"ONGC","expiry":"Apr-2021","lot":"7700","price":"114.70","nrml":"459797","mis":"229898.5","co_margin":"240845.91","bo_margin":"240845.91"},{"scrip":"ONGC","expiry":"May-2021","lot":"7700","price":"114.80","nrml":"461137","mis":"230568.5","co_margin":"241055.89","bo_margin":"241055.89"},{"scrip":"PAGEIND","expiry":"Mar-2021","lot":"30","price":"28328.05","nrml":"202151","mis":"101075.5","co_margin":"107759.9","bo_margin":"107759.9"},{"scrip":"PAGEIND","expiry":"Apr-2021","lot":"30","price":"28391.50","nrml":"202922","mis":"101461","co_margin":"108001.27","bo_margin":"108001.27"},{"scrip":"PAGEIND","expiry":"May-2021","lot":"30","price":"28556.60","nrml":"204011","mis":"102005.5","co_margin":"108629.31","bo_margin":"108629.31"},{"scrip":"PEL","expiry":"Mar-2021","lot":"550","price":"1957.65","nrml":"521010","mis":"260505","co_margin":"283174.07","bo_margin":"283174.07"},{"scrip":"PEL","expiry":"Apr-2021","lot":"550","price":"1962.05","nrml":"522909","mis":"261454.5","co_margin":"283810.53","bo_margin":"283810.53"},{"scrip":"PEL","expiry":"May-2021","lot":"550","price":"1973.45","nrml":"523849","mis":"261924.5","co_margin":"285459.54","bo_margin":"285459.54"},{"scrip":"PETRONET","expiry":"Mar-2021","lot":"3000","price":"246.60","nrml":"205237","mis":"102618.5","co_margin":"105125.58","bo_margin":"105125.58"},{"scrip":"PETRONET","expiry":"Apr-2021","lot":"3000","price":"247.15","nrml":"206081","mis":"103040.5","co_margin":"105360.05","bo_margin":"105360.05"},{"scrip":"PETRONET","expiry":"May-2021","lot":"3000","price":"248.60","nrml":"206790","mis":"103395","co_margin":"105978.18","bo_margin":"105978.18"},{"scrip":"PFC","expiry":"Mar-2021","lot":"6200","price":"134.40","nrml":"215054","mis":"107527","co_margin":"115409.28","bo_margin":"115409.28"},{"scrip":"PFC","expiry":"Apr-2021","lot":"6200","price":"134.70","nrml":"215791","mis":"107895.5","co_margin":"115666.89","bo_margin":"115666.89"},{"scrip":"PFC","expiry":"May-2021","lot":"6200","price":"135.50","nrml":"216417","mis":"108208.5","co_margin":"116353.85","bo_margin":"116353.85"},{"scrip":"PFIZER","expiry":"Mar-2021","lot":"125","price":"4638.50","nrml":"124629","mis":"62314.5","co_margin":"64185.24","bo_margin":"64185.24"},{"scrip":"PFIZER","expiry":"Apr-2021","lot":"125","price":"4648.90","nrml":"125039","mis":"62519.5","co_margin":"64329.15","bo_margin":"64329.15"},{"scrip":"PFIZER","expiry":"May-2021","lot":"125","price":"4675.95","nrml":"125413","mis":"62706.5","co_margin":"64703.46","bo_margin":"64703.46"},{"scrip":"PIDILITIND","expiry":"Mar-2021","lot":"500","price":"1737.00","nrml":"171602","mis":"85801","co_margin":"87805.35","bo_margin":"87805.35"},{"scrip":"PIDILITIND","expiry":"Apr-2021","lot":"500","price":"1740.90","nrml":"172256","mis":"86128","co_margin":"88002.5","bo_margin":"88002.5"},{"scrip":"PIDILITIND","expiry":"May-2021","lot":"500","price":"1751.05","nrml":"172967","mis":"86483.5","co_margin":"88515.58","bo_margin":"88515.58"},{"scrip":"PIIND","expiry":"Mar-2021","lot":"250","price":"2289.85","nrml":"130885","mis":"65442.5","co_margin":"67951.3","bo_margin":"67951.3"},{"scrip":"PIIND","expiry":"Apr-2021","lot":"250","price":"2295.00","nrml":"131450","mis":"65725","co_margin":"68104.13","bo_margin":"68104.13"},{"scrip":"PIIND","expiry":"May-2021","lot":"250","price":"2308.35","nrml":"131046","mis":"65523","co_margin":"68500.29","bo_margin":"68500.29"},{"scrip":"PNB","expiry":"Mar-2021","lot":"16000","price":"41.50","nrml":"273290","mis":"136645","co_margin":"162680","bo_margin":"162680"},{"scrip":"PNB","expiry":"Apr-2021","lot":"16000","price":"41.60","nrml":"274300","mis":"137150","co_margin":"163072","bo_margin":"163072"},{"scrip":"PNB","expiry":"May-2021","lot":"16000","price":"41.85","nrml":"278020","mis":"139010","co_margin":"164052","bo_margin":"164052"},{"scrip":"POWERGRID","expiry":"Mar-2021","lot":"4000","price":"215.15","nrml":"178310","mis":"89155","co_margin":"92084.2","bo_margin":"92084.2"},{"scrip":"POWERGRID","expiry":"Apr-2021","lot":"4000","price":"215.65","nrml":"178956","mis":"89478","co_margin":"92298.2","bo_margin":"92298.2"},{"scrip":"POWERGRID","expiry":"May-2021","lot":"4000","price":"216.90","nrml":"181118","mis":"90559","co_margin":"92833.2","bo_margin":"92833.2"},{"scrip":"PVR","expiry":"Mar-2021","lot":"407","price":"1442.85","nrml":"250207","mis":"125103.5","co_margin":"134712.84","bo_margin":"134712.84"},{"scrip":"PVR","expiry":"Apr-2021","lot":"407","price":"1446.10","nrml":"251116","mis":"125558","co_margin":"135016.28","bo_margin":"135016.28"},{"scrip":"PVR","expiry":"May-2021","lot":"407","price":"1454.50","nrml":"251800","mis":"125900","co_margin":"135800.56","bo_margin":"135800.56"},{"scrip":"RAMCOCEM","expiry":"Mar-2021","lot":"850","price":"1019.10","nrml":"189616","mis":"94808","co_margin":"98577.54","bo_margin":"98577.54"},{"scrip":"RAMCOCEM","expiry":"Apr-2021","lot":"850","price":"1021.40","nrml":"190323","mis":"95161.5","co_margin":"98800.02","bo_margin":"98800.02"},{"scrip":"RAMCOCEM","expiry":"May-2021","lot":"850","price":"1027.35","nrml":"189853","mis":"94926.5","co_margin":"99375.57","bo_margin":"99375.57"},{"scrip":"RBLBANK","expiry":"Mar-2021","lot":"2900","price":"241.90","nrml":"264051","mis":"132025.5","co_margin":"138127.32","bo_margin":"138127.32"},{"scrip":"RBLBANK","expiry":"Apr-2021","lot":"2900","price":"242.45","nrml":"264982","mis":"132491","co_margin":"138441.37","bo_margin":"138441.37"},{"scrip":"RBLBANK","expiry":"May-2021","lot":"2900","price":"243.55","nrml":"265739","mis":"132869.5","co_margin":"139069.49","bo_margin":"139069.49"},{"scrip":"RECLTD","expiry":"Mar-2021","lot":"6000","price":"151.20","nrml":"226623","mis":"113311.5","co_margin":"121474.08","bo_margin":"121474.08"},{"scrip":"RECLTD","expiry":"Apr-2021","lot":"6000","price":"151.55","nrml":"227430","mis":"113715","co_margin":"121755.27","bo_margin":"121755.27"},{"scrip":"RECLTD","expiry":"May-2021","lot":"6000","price":"149.35","nrml":"228135","mis":"114067.5","co_margin":"119987.79","bo_margin":"119987.79"},{"scrip":"RELIANCE","expiry":"Mar-2021","lot":"250","price":"2181.95","nrml":"129311","mis":"64655.5","co_margin":"66331.28","bo_margin":"66331.28"},{"scrip":"RELIANCE","expiry":"Apr-2021","lot":"250","price":"2186.85","nrml":"129822","mis":"64911","co_margin":"66480.24","bo_margin":"66480.24"},{"scrip":"RELIANCE","expiry":"May-2021","lot":"250","price":"2212.00","nrml":"130247","mis":"65123.5","co_margin":"67244.8","bo_margin":"67244.8"},{"scrip":"SAIL","expiry":"Mar-2021","lot":"19000","price":"73.00","nrml":"611526","mis":"305763","co_margin":"333712.2","bo_margin":"333712.2"},{"scrip":"SAIL","expiry":"Apr-2021","lot":"19000","price":"73.20","nrml":"615231","mis":"307615.5","co_margin":"334626.48","bo_margin":"334626.48"},{"scrip":"SAIL","expiry":"May-2021","lot":"19000","price":"73.60","nrml":"627059","mis":"313529.5","co_margin":"336455.04","bo_margin":"336455.04"},{"scrip":"SBILIFE","expiry":"Mar-2021","lot":"750","price":"940.70","nrml":"163517","mis":"81758.5","co_margin":"83886.92","bo_margin":"83886.92"},{"scrip":"SBILIFE","expiry":"Apr-2021","lot":"750","price":"942.85","nrml":"164091","mis":"82045.5","co_margin":"84078.65","bo_margin":"84078.65"},{"scrip":"SBILIFE","expiry":"May-2021","lot":"750","price":"954.85","nrml":"164767","mis":"82383.5","co_margin":"85148.75","bo_margin":"85148.75"},{"scrip":"SBIN","expiry":"Mar-2021","lot":"3000","price":"387.70","nrml":"409441","mis":"204720.5","co_margin":"212963.61","bo_margin":"212963.61"},{"scrip":"SBIN","expiry":"Apr-2021","lot":"3000","price":"388.60","nrml":"410997","mis":"205498.5","co_margin":"213457.98","bo_margin":"213457.98"},{"scrip":"SBIN","expiry":"May-2021","lot":"3000","price":"394.05","nrml":"412278","mis":"206139","co_margin":"216451.67","bo_margin":"216451.67"},{"scrip":"SHREECEM","expiry":"Mar-2021","lot":"50","price":"27556.35","nrml":"309154","mis":"154577","co_margin":"163960.28","bo_margin":"163960.28"},{"scrip":"SHREECEM","expiry":"Apr-2021","lot":"50","price":"27618.05","nrml":"310579","mis":"155289.5","co_margin":"164327.4","bo_margin":"164327.4"},{"scrip":"SHREECEM","expiry":"May-2021","lot":"50","price":"27864.00","nrml":"311322","mis":"155661","co_margin":"165790.8","bo_margin":"165790.8"},{"scrip":"SIEMENS","expiry":"Mar-2021","lot":"550","price":"1905.10","nrml":"223005","mis":"111502.5","co_margin":"116620.7","bo_margin":"116620.7"},{"scrip":"SIEMENS","expiry":"Apr-2021","lot":"550","price":"1909.40","nrml":"223830","mis":"111915","co_margin":"116883.92","bo_margin":"116883.92"},{"scrip":"SIEMENS","expiry":"May-2021","lot":"550","price":"1920.50","nrml":"224461","mis":"112230.5","co_margin":"117563.41","bo_margin":"117563.41"},{"scrip":"SRF","expiry":"Mar-2021","lot":"125","price":"5658.70","nrml":"172256","mis":"86128","co_margin":"89902.6","bo_margin":"89902.6"},{"scrip":"SRF","expiry":"Apr-2021","lot":"125","price":"5671.40","nrml":"172993","mis":"86496.5","co_margin":"90104.37","bo_margin":"90104.37"},{"scrip":"SRF","expiry":"May-2021","lot":"125","price":"5704.35","nrml":"173564","mis":"86782","co_margin":"90627.86","bo_margin":"90627.86"},{"scrip":"SRTRANSFIN","expiry":"Mar-2021","lot":"800","price":"1315.40","nrml":"373496","mis":"186748","co_margin":"206886.11","bo_margin":"206886.11"},{"scrip":"SRTRANSFIN","expiry":"Apr-2021","lot":"800","price":"1318.35","nrml":"374833","mis":"187416.5","co_margin":"207350.09","bo_margin":"207350.09"},{"scrip":"SRTRANSFIN","expiry":"May-2021","lot":"800","price":"1326.05","nrml":"375432","mis":"187716","co_margin":"208561.14","bo_margin":"208561.14"},{"scrip":"SUNPHARMA","expiry":"Mar-2021","lot":"1400","price":"626.00","nrml":"206784","mis":"103392","co_margin":"107709.56","bo_margin":"107709.56"},{"scrip":"SUNPHARMA","expiry":"Apr-2021","lot":"1400","price":"627.40","nrml":"207615","mis":"103807.5","co_margin":"107950.44","bo_margin":"107950.44"},{"scrip":"SUNPHARMA","expiry":"May-2021","lot":"1400","price":"633.25","nrml":"208239","mis":"104119.5","co_margin":"108957","bo_margin":"108957"},{"scrip":"SUNTV","expiry":"Mar-2021","lot":"1500","price":"489.00","nrml":"298918","mis":"149459","co_margin":"155502","bo_margin":"155502"},{"scrip":"SUNTV","expiry":"Apr-2021","lot":"1500","price":"490.10","nrml":"300516","mis":"150258","co_margin":"155851.8","bo_margin":"155851.8"},{"scrip":"SUNTV","expiry":"May-2021","lot":"1500","price":"492.95","nrml":"311234","mis":"155617","co_margin":"156758.1","bo_margin":"156758.1"},{"scrip":"TATACHEM","expiry":"Mar-2021","lot":"2000","price":"767.00","nrml":"400866","mis":"200433","co_margin":"207857","bo_margin":"207857"},{"scrip":"TATACHEM","expiry":"Apr-2021","lot":"2000","price":"768.75","nrml":"402458","mis":"201229","co_margin":"208331.25","bo_margin":"208331.25"},{"scrip":"TATACHEM","expiry":"May-2021","lot":"2000","price":"773.20","nrml":"403960","mis":"201980","co_margin":"209537.2","bo_margin":"209537.2"},{"scrip":"TATACONSUM","expiry":"Mar-2021","lot":"1350","price":"620.95","nrml":"224450","mis":"112225","co_margin":"116772.75","bo_margin":"116772.75"},{"scrip":"TATACONSUM","expiry":"Apr-2021","lot":"1350","price":"622.35","nrml":"225268","mis":"112634","co_margin":"117036.03","bo_margin":"117036.03"},{"scrip":"TATACONSUM","expiry":"May-2021","lot":"1350","price":"630.80","nrml":"226008","mis":"113004","co_margin":"118625.09","bo_margin":"118625.09"},{"scrip":"TATAMOTORS","expiry":"Mar-2021","lot":"5700","price":"321.45","nrml":"625975","mis":"312987.5","co_margin":"336220.63","bo_margin":"336220.63"},{"scrip":"TATAMOTORS","expiry":"Apr-2021","lot":"5700","price":"322.20","nrml":"628339","mis":"314169.5","co_margin":"337005.09","bo_margin":"337005.09"},{"scrip":"TATAMOTORS","expiry":"May-2021","lot":"5700","price":"326.70","nrml":"630331","mis":"315165.5","co_margin":"341711.87","bo_margin":"341711.87"},{"scrip":"TATAPOWER","expiry":"Mar-2021","lot":"13500","price":"107.35","nrml":"410875","mis":"205437.5","co_margin":"215644.68","bo_margin":"215644.68"},{"scrip":"TATAPOWER","expiry":"Apr-2021","lot":"13500","price":"107.60","nrml":"412303","mis":"206151.5","co_margin":"216146.88","bo_margin":"216146.88"},{"scrip":"TATAPOWER","expiry":"May-2021","lot":"13500","price":"108.25","nrml":"413709","mis":"206854.5","co_margin":"217452.6","bo_margin":"217452.6"},{"scrip":"TATASTEEL","expiry":"Mar-2021","lot":"1700","price":"724.50","nrml":"382568","mis":"191284","co_margin":"206794.04","bo_margin":"206794.04"},{"scrip":"TATASTEEL","expiry":"Apr-2021","lot":"1700","price":"726.15","nrml":"383982","mis":"191991","co_margin":"207264.99","bo_margin":"207264.99"},{"scrip":"TATASTEEL","expiry":"May-2021","lot":"1700","price":"731.20","nrml":"385126","mis":"192563","co_margin":"208706.42","bo_margin":"208706.42"},{"scrip":"TCS","expiry":"Mar-2021","lot":"300","price":"3070.95","nrml":"192831","mis":"96415.5","co_margin":"99867.29","bo_margin":"99867.29"},{"scrip":"TCS","expiry":"Apr-2021","lot":"300","price":"3077.85","nrml":"193620","mis":"96810","co_margin":"100091.68","bo_margin":"100091.68"},{"scrip":"TCS","expiry":"May-2021","lot":"300","price":"3119.25","nrml":"194208","mis":"97104","co_margin":"101438.01","bo_margin":"101438.01"},{"scrip":"TECHM","expiry":"Mar-2021","lot":"1200","price":"1008.75","nrml":"270798","mis":"135399","co_margin":"142960.05","bo_margin":"142960.05"},{"scrip":"TECHM","expiry":"Apr-2021","lot":"1200","price":"1011.05","nrml":"271861","mis":"135930.5","co_margin":"143286.01","bo_margin":"143286.01"},{"scrip":"TECHM","expiry":"May-2021","lot":"1200","price":"1022.00","nrml":"272736","mis":"136368","co_margin":"144837.84","bo_margin":"144837.84"},{"scrip":"TITAN","expiry":"Mar-2021","lot":"750","price":"1471.25","nrml":"246742","mis":"123371","co_margin":"127778.06","bo_margin":"127778.06"},{"scrip":"TITAN","expiry":"Apr-2021","lot":"750","price":"1474.55","nrml":"247657","mis":"123828.5","co_margin":"128064.67","bo_margin":"128064.67"},{"scrip":"TITAN","expiry":"May-2021","lot":"750","price":"1483.15","nrml":"248073","mis":"124036.5","co_margin":"128811.58","bo_margin":"128811.58"},{"scrip":"TORNTPHARM","expiry":"Mar-2021","lot":"250","price":"2445.20","nrml":"134561","mis":"67280.5","co_margin":"69688.2","bo_margin":"69688.2"},{"scrip":"TORNTPHARM","expiry":"Apr-2021","lot":"250","price":"2450.70","nrml":"135062","mis":"67531","co_margin":"69844.95","bo_margin":"69844.95"},{"scrip":"TORNTPHARM","expiry":"May-2021","lot":"250","price":"2464.95","nrml":"135865","mis":"67932.5","co_margin":"70251.08","bo_margin":"70251.08"},{"scrip":"TORNTPOWER","expiry":"Mar-2021","lot":"3000","price":"417.50","nrml":"278728","mis":"139364","co_margin":"147294","bo_margin":"147294"},{"scrip":"TORNTPOWER","expiry":"Apr-2021","lot":"3000","price":"418.45","nrml":"279311","mis":"139655.5","co_margin":"147629.16","bo_margin":"147629.16"},{"scrip":"TORNTPOWER","expiry":"May-2021","lot":"3000","price":"420.90","nrml":"277869","mis":"138934.5","co_margin":"148493.52","bo_margin":"148493.52"},{"scrip":"TRENT","expiry":"Mar-2021","lot":"725","price":"912.25","nrml":"185408","mis":"92704","co_margin":"99802.43","bo_margin":"99802.43"},{"scrip":"TRENT","expiry":"Apr-2021","lot":"725","price":"914.30","nrml":"185861","mis":"92930.5","co_margin":"100026.71","bo_margin":"100026.71"},{"scrip":"TRENT","expiry":"May-2021","lot":"725","price":"919.65","nrml":"186521","mis":"93260.5","co_margin":"100612.01","bo_margin":"100612.01"},{"scrip":"TVSMOTOR","expiry":"Mar-2021","lot":"1400","price":"603.15","nrml":"200999","mis":"100499.5","co_margin":"105297.93","bo_margin":"105297.93"},{"scrip":"TVSMOTOR","expiry":"Apr-2021","lot":"1400","price":"604.50","nrml":"201642","mis":"100821","co_margin":"105533.61","bo_margin":"105533.61"},{"scrip":"TVSMOTOR","expiry":"May-2021","lot":"1400","price":"608.05","nrml":"203303","mis":"101651.5","co_margin":"106153.37","bo_margin":"106153.37"},{"scrip":"UBL","expiry":"Mar-2021","lot":"700","price":"1230.55","nrml":"191832","mis":"95916","co_margin":"98800.86","bo_margin":"98800.86"},{"scrip":"UBL","expiry":"Apr-2021","lot":"700","price":"1233.30","nrml":"192531","mis":"96265.5","co_margin":"99021.66","bo_margin":"99021.66"},{"scrip":"UBL","expiry":"May-2021","lot":"700","price":"1240.50","nrml":"192414","mis":"96207","co_margin":"99599.75","bo_margin":"99599.75"},{"scrip":"ULTRACEMCO","expiry":"Mar-2021","lot":"200","price":"6764.15","nrml":"387378","mis":"193689","co_margin":"202924.5","bo_margin":"202924.5"},{"scrip":"ULTRACEMCO","expiry":"Apr-2021","lot":"200","price":"6779.30","nrml":"388862","mis":"194431","co_margin":"203379","bo_margin":"203379"},{"scrip":"ULTRACEMCO","expiry":"May-2021","lot":"200","price":"6818.75","nrml":"389724","mis":"194862","co_margin":"204562.5","bo_margin":"204562.5"},{"scrip":"UPL","expiry":"Mar-2021","lot":"1300","price":"621.30","nrml":"236757","mis":"118378.5","co_margin":"121961.19","bo_margin":"121961.19"},{"scrip":"UPL","expiry":"Apr-2021","lot":"1300","price":"622.70","nrml":"237652","mis":"118826","co_margin":"122236.01","bo_margin":"122236.01"},{"scrip":"UPL","expiry":"May-2021","lot":"1300","price":"630.10","nrml":"238334","mis":"119167","co_margin":"123688.63","bo_margin":"123688.63"},{"scrip":"VEDL","expiry":"Mar-2021","lot":"6200","price":"226.25","nrml":"488398","mis":"244199","co_margin":"259087.93","bo_margin":"259087.93"},{"scrip":"VEDL","expiry":"Apr-2021","lot":"6200","price":"226.80","nrml":"490187","mis":"245093.5","co_margin":"259717.75","bo_margin":"259717.75"},{"scrip":"VEDL","expiry":"May-2021","lot":"6200","price":"230.10","nrml":"492053","mis":"246026.5","co_margin":"263496.71","bo_margin":"263496.71"},{"scrip":"VOLTAS","expiry":"Mar-2021","lot":"1000","price":"1061.60","nrml":"233492","mis":"116746","co_margin":"125693.44","bo_margin":"125693.44"},{"scrip":"VOLTAS","expiry":"Apr-2021","lot":"1000","price":"1064.00","nrml":"234379","mis":"117189.5","co_margin":"125977.6","bo_margin":"125977.6"},{"scrip":"VOLTAS","expiry":"May-2021","lot":"1000","price":"1070.20","nrml":"234960","mis":"117480","co_margin":"126711.68","bo_margin":"126711.68"},{"scrip":"WIPRO","expiry":"Mar-2021","lot":"3200","price":"426.70","nrml":"297204","mis":"148602","co_margin":"159893.02","bo_margin":"159893.02"},{"scrip":"WIPRO","expiry":"Apr-2021","lot":"3200","price":"427.70","nrml":"298246","mis":"149123","co_margin":"160267.74","bo_margin":"160267.74"},{"scrip":"WIPRO","expiry":"May-2021","lot":"3200","price":"431.70","nrml":"299230","mis":"149615","co_margin":"161766.62","bo_margin":"161766.62"},{"scrip":"ZEEL","expiry":"Mar-2021","lot":"3000","price":"221.65","nrml":"258384","mis":"129192","co_margin":"137578.16","bo_margin":"137578.16"},{"scrip":"ZEEL","expiry":"Apr-2021","lot":"3000","price":"222.15","nrml":"259361","mis":"129680.5","co_margin":"137888.51","bo_margin":"137888.51"},{"scrip":"ZEEL","expiry":"May-2021","lot":"3000","price":"223.45","nrml":"259909","mis":"129954.5","co_margin":"138695.42","bo_margin":"138695.42"}]