[{"scrip":"91DTB","expiry":"Sep 2019","lot":"2000","price":"94.21","nrml":150,"mis":75,"co_lower":0,"co_upper":0},{"scrip":"EURINR","expiry":"Sep 2019","lot":"1000","price":"79.23","nrml":1830,"mis":915,"co_lower":0.85,"co_upper":1.155},{"scrip":"EURINR","expiry":"Oct 2019","lot":"1000","price":"79.75","nrml":1842,"mis":921,"co_lower":0.85,"co_upper":1.155},{"scrip":"EURUSD","expiry":"Sep 2019","lot":"1000","price":"78.45","nrml":2361,"mis":1180,"co_lower":0,"co_upper":0},{"scrip":"EURUSD","expiry":"Oct 2019","lot":"1000","price":"78.65","nrml":2367,"mis":1183,"co_lower":0,"co_upper":0},{"scrip":"717GS2028","expiry":"Aug 2019","lot":"2000","price":"100.95","nrml":4038,"mis":2019,"co_lower":0,"co_upper":0},{"scrip":"717GS2028","expiry":"Sep 2019","lot":"2000","price":"100.84","nrml":4033,"mis":2016,"co_lower":0,"co_upper":0},{"scrip":"726GS2029","expiry":"Aug 2019","lot":"2000","price":"102.58","nrml":4103,"mis":2051,"co_lower":0,"co_upper":0},{"scrip":"726GS2029","expiry":"Sep 2019","lot":"2000","price":"102.48","nrml":4099,"mis":2049,"co_lower":0,"co_upper":0},{"scrip":"668GS2031","expiry":"Aug 2019","lot":"2000","price":"97.19","nrml":3887,"mis":1943,"co_lower":0,"co_upper":0},{"scrip":"668GS2031","expiry":"Sep 2019","lot":"2000","price":"97.11","nrml":3884,"mis":1942,"co_lower":0,"co_upper":0},{"scrip":"795GS2032","expiry":"Aug 2019","lot":"2000","price":"107.66","nrml":4306,"mis":2153,"co_lower":0,"co_upper":0},{"scrip":"795GS2032","expiry":"Sep 2019","lot":"2000","price":"107.52","nrml":4300,"mis":2150,"co_lower":0,"co_upper":0},{"scrip":"768GS2023","expiry":"Aug 2019","lot":"2000","price":"103.09","nrml":4123,"mis":2061,"co_lower":0,"co_upper":0},{"scrip":"768GS2023","expiry":"Sep 2019","lot":"2000","price":"102.96","nrml":4118,"mis":2059,"co_lower":0,"co_upper":0},{"scrip":"GBPINR","expiry":"Sep 2019","lot":"1000","price":"88.28","nrml":2207,"mis":1103,"co_lower":1.05,"co_upper":1.255},{"scrip":"GBPINR","expiry":"Oct 2019","lot":"1000","price":"88.77","nrml":2219,"mis":1109,"co_lower":1.05,"co_upper":1.26},{"scrip":"GBPUSD","expiry":"Sep 2019","lot":"1000","price":"87.5","nrml":2633,"mis":1316,"co_lower":0,"co_upper":0},{"scrip":"GBPUSD","expiry":"Oct 2019","lot":"1000","price":"87.62","nrml":2637,"mis":1318,"co_lower":0,"co_upper":0},{"scrip":"JPYINR","expiry":"Sep 2019","lot":"1000","price":"64.71","nrml":1947,"mis":973,"co_lower":1.3,"co_upper":1.505},{"scrip":"JPYINR","expiry":"Oct 2019","lot":"1000","price":"65.11","nrml":1959,"mis":979,"co_lower":1.3,"co_upper":1.505},{"scrip":"USDINR","expiry":"Sep 2019","lot":"1000","price":"69.69","nrml":1400,"mis":700,"co_lower":0.85,"co_upper":1.045},{"scrip":"USDINR","expiry":"Oct 2019","lot":"1000","price":"69.97","nrml":1406,"mis":703,"co_lower":0.85,"co_upper":1.045},{"scrip":"USDJPY","expiry":"Sep 2019","lot":"1000","price":"68.48","nrml":2061,"mis":1030,"co_lower":0,"co_upper":0},{"scrip":"USDJPY","expiry":"Oct 2019","lot":"1000","price":"68.33","nrml":2056,"mis":1028,"co_lower":0,"co_upper":0}]